{
  "yvNo": "23440201",
  "id": "181537",
  "Brand_Reference": "181537",
  "crossNumbers": [
    {
      "maker": "ATE",
      "crossNumber": "13.0460-7186.2"
    },
    {
      "maker": "ATE",
      "crossNumber": "607186"
    },
    {
      "maker": "B.M.",
      "crossNumber": "DB1666"
    },
    {
      "maker": "BENDIX ANTIGUO",
      "crossNumber": "573085B"
    },
    {
      "maker": "BENDIX-ROULUNDS",
      "crossNumber": "510374"
    },
    {
      "maker": "BOSCH",
      "crossNumber": "0 986 424 701"
    },
    {
      "maker": "BREMBO",
      "crossNumber": "P 24 058"
    },
    {
      "maker": "BREMBO",
      "crossNumber": "P 24 071"
    },
    {
      "maker": "DELPHI LOCKHEED",
      "crossNumber": "LP1724"
    },
    {
      "maker": "FERODO",
      "crossNumber": "FDB1568"
    },
    {
      "maker": "FERODO",
      "crossNumber": "FDS1568"
    },
    {
      "maker": "FERODO",
      "crossNumber": "FVR1568"
    },
    {
      "maker": "FMSI",
      "crossNumber": "D970-7871"
    },
    {
      "maker": "GIRLING",
      "crossNumber": "6115322"
    },
    {
      "maker": "HELLA-PAGID",
      "crossNumber": "8DB 355 009-561"
    },
    {
      "maker": "HELLA-PAGID",
      "crossNumber": "T1261"
    },
    {
      "maker": "HELLA-PAGID",
      "crossNumber": "T1528"
    },
    {
      "maker": "MINTEX",
      "crossNumber": "MDB2272"
    },
    {
      "maker": "MINTEX",
      "crossNumber": "MDB2793"
    },
    {
      "maker": "NECTO",
      "crossNumber": "FD7034V"
    },
    {
      "maker": "ROAD HOUSE",
      "crossNumber": "2984.00"
    },
    {
      "maker": "TEXTAR",
      "crossNumber": "23440 171  0 5 T4149"
    },
    {
      "maker": "TEXTAR",
      "crossNumber": "23440 171 0 5"
    },
    {
      "maker": "TEXTAR",
      "crossNumber": "23440 176  0 5 T4149"
    },
    {
      "maker": "TEXTAR",
      "crossNumber": "234400 176 0 5"
    },
    {
      "maker": "TEXTAR",
      "crossNumber": "2344004"
    },
    {
      "maker": "TEXTAR",
      "crossNumber": "2344007"
    },
    {
      "maker": "TRW",
      "crossNumber": "GDB1532"
    },
    {
      "maker": "VALEO",
      "crossNumber": "598639"
    },
    {
      "maker": "WVA",
      "crossNumber": "23440"
    },
    {
      "maker": "WVA",
      "crossNumber": "23441"
    }
  ]
}