{
  "reference": "2334001",
  "id": "2334001",
  "name": "Fren balata seti, diskli fren",
  "brand": "TEXTAR",
  "wvaNumbers": [
    "23340",
    "23340 168  1 5",
    "23341",
    "23342",
    "8674D1475"
  ],
  "brand_oe_map": {
    "TOYOTA": [
      "044650D010",
      "044650D040",
      "04465YZZCR",
      "04465YZZCRA",
      "04465YZZEM"
    ]
  },
  "eanNumber": "4019722265242",
  "dimensions": {
    "width1": "130,7",
    "width2": null,
    "height1": "45",
    "height2": "51,5",
    "thickness1": "16,8",
    "thickness2": null,
    "manufacturerRestriction": "",
    "checkmark": "",
    "SVHC": ""
  }
}