[
  {
    "brand": "BMW",
    "model": "5 (F10)",
    "engineType": "518 d",
    "madeYear": "07.2013 - 10.2016",
    "kw": "100",
    "hp": "136",
    "cc": "1995",
    "engineCodes": "N47 D20 C  B47 D20 A",
    "KBA_Numbers": "0005BQC"
  },
  {
    "brand": "BMW",
    "model": "5 (F10)",
    "engineType": "518 d",
    "madeYear": "07.2013 - 06.2014",
    "kw": "105",
    "hp": "143",
    "cc": "1995",
    "engineCodes": "N47 D20 C",
    "KBA_Numbers": "0005BQD"
  },
  {
    "brand": "BMW",
    "model": "5 (F10)",
    "engineType": "518 d",
    "madeYear": "10.2013 - 10.2016",
    "kw": "120",
    "hp": "163",
    "cc": "1995",
    "engineCodes": "B47 D20 A",
    "KBA_Numbers": ""
  },
  {
    "brand": "BMW",
    "model": "5 (F10)",
    "engineType": "518 d",
    "madeYear": "07.2014 - 10.2016",
    "kw": "110",
    "hp": "150",
    "cc": "1995",
    "engineCodes": "B47 D20 A",
    "KBA_Numbers": "0005BWU"
  },
  {
    "brand": "BMW",
    "model": "5 (F10)",
    "engineType": "520 d",
    "madeYear": "06.2010 - 10.2016",
    "kw": "120",
    "hp": "163",
    "cc": "1995",
    "engineCodes": "B47 D20 A  N47 D20 C",
    "KBA_Numbers": "0005ATH"
  },
  {
    "brand": "BMW",
    "model": "5 (F10)",
    "engineType": "520 d",
    "madeYear": "06.2010 - 06.2014",
    "kw": "135",
    "hp": "184",
    "cc": "1995",
    "engineCodes": "N47 D20 C",
    "KBA_Numbers": "0005ATE"
  },
  {
    "brand": "BMW",
    "model": "5 (F10)",
    "engineType": "520 d",
    "madeYear": "06.2010 - 06.2014",
    "kw": "147",
    "hp": "200",
    "cc": "1995",
    "engineCodes": "N47 D20 C",
    "KBA_Numbers": "0005BEO"
  },
  {
    "brand": "BMW",
    "model": "5 (F10)",
    "engineType": "520 d",
    "madeYear": "01.2013 - 06.2014",
    "kw": "100",
    "hp": "136",
    "cc": "1995",
    "engineCodes": "N47 D20 C",
    "KBA_Numbers": ""
  },
  {
    "brand": "BMW",
    "model": "5 (F10)",
    "engineType": "520 d",
    "madeYear": "10.2013 - 10.2016",
    "kw": "155",
    "hp": "211",
    "cc": "1995",
    "engineCodes": "B47 D20 A",
    "KBA_Numbers": ""
  },
  {
    "brand": "BMW",
    "model": "5 (F10)",
    "engineType": "520 d",
    "madeYear": "07.2014 - 10.2016",
    "kw": "140",
    "hp": "190",
    "cc": "1995",
    "engineCodes": "B47 D20 A",
    "KBA_Numbers": "0005BWV"
  },
  {
    "brand": "BMW",
    "model": "5 (F10)",
    "engineType": "520 d",
    "madeYear": "07.2014 - 10.2016",
    "kw": "151",
    "hp": "205",
    "cc": "1995",
    "engineCodes": "B47 D20 A",
    "KBA_Numbers": "0005BZM"
  },
  {
    "brand": "BMW",
    "model": "5 (F10)",
    "engineType": "520 d xDrive",
    "madeYear": "01.2013 - 06.2014",
    "kw": "100",
    "hp": "136",
    "cc": "1995",
    "engineCodes": "N47 D20 C",
    "KBA_Numbers": ""
  },
  {
    "brand": "BMW",
    "model": "5 (F10)",
    "engineType": "520 d xDrive",
    "madeYear": "01.2013 - 06.2014",
    "kw": "147",
    "hp": "200",
    "cc": "1995",
    "engineCodes": "N47 D20 C",
    "KBA_Numbers": "0005BQF"
  },
  {
    "brand": "BMW",
    "model": "5 (F10)",
    "engineType": "520 d xDrive",
    "madeYear": "07.2013 - 10.2016",
    "kw": "120",
    "hp": "163",
    "cc": "1995",
    "engineCodes": "B47 D20 A  N47 D20 C",
    "KBA_Numbers": "0005BQE"
  },
  {
    "brand": "BMW",
    "model": "5 (F10)",
    "engineType": "520 d xDrive",
    "madeYear": "07.2013 - 06.2014",
    "kw": "135",
    "hp": "184",
    "cc": "1995",
    "engineCodes": "N47 D20 C",
    "KBA_Numbers": "0005BQG"
  },
  {
    "brand": "BMW",
    "model": "5 (F10)",
    "engineType": "520 d xDrive",
    "madeYear": "10.2013 - 10.2016",
    "kw": "155",
    "hp": "211",
    "cc": "1995",
    "engineCodes": "B47 D20 A",
    "KBA_Numbers": "0005BFU"
  },
  {
    "brand": "BMW",
    "model": "5 (F10)",
    "engineType": "520 d xDrive",
    "madeYear": "07.2014 - 10.2016",
    "kw": "140",
    "hp": "190",
    "cc": "1995",
    "engineCodes": "B47 D20 A",
    "KBA_Numbers": "0005BWW"
  },
  {
    "brand": "BMW",
    "model": "5 (F10)",
    "engineType": "520 d xDrive",
    "madeYear": "07.2014 - 10.2016",
    "kw": "151",
    "hp": "205",
    "cc": "1995",
    "engineCodes": "B47 D20 A",
    "KBA_Numbers": "0005BZN"
  },
  {
    "brand": "BMW",
    "model": "5 (F10)",
    "engineType": "520 i",
    "madeYear": "09.2011 - 10.2016",
    "kw": "120",
    "hp": "163",
    "cc": "1997",
    "engineCodes": "N20 B20 B  N20 B20 A",
    "KBA_Numbers": "0005BFM"
  },
  {
    "brand": "BMW",
    "model": "5 (F10)",
    "engineType": "520 i",
    "madeYear": "09.2011 - 10.2016",
    "kw": "135",
    "hp": "184",
    "cc": "1997",
    "engineCodes": "N20 B20 A  N20 B20 B",
    "KBA_Numbers": "0005BFL  0005BFN"
  },
  {
    "brand": "BMW",
    "model": "5 (F10)",
    "engineType": "523 i",
    "madeYear": "06.2009 - 08.2011",
    "kw": "150",
    "hp": "204",
    "cc": "2996",
    "engineCodes": "N53 B30 A",
    "KBA_Numbers": "0005ATA"
  },
  {
    "brand": "BMW",
    "model": "5 (F10)",
    "engineType": "523 i",
    "madeYear": "01.2010 - 08.2011",
    "kw": "150",
    "hp": "204",
    "cc": "2497",
    "engineCodes": "N52 B25 B  N52 B25 AF  N52 B25 BF  N52 B25 A",
    "KBA_Numbers": "0005AYS"
  },
  {
    "brand": "BMW",
    "model": "5 (F10)",
    "engineType": "523 i",
    "madeYear": "01.2010 - 08.2011",
    "kw": "155",
    "hp": "211",
    "cc": "2996",
    "engineCodes": "N53 B30 A",
    "KBA_Numbers": "0005AIM"
  },
  {
    "brand": "BMW",
    "model": "5 (F10)",
    "engineType": "525 d",
    "madeYear": "03.2010 - 08.2011",
    "kw": "150",
    "hp": "204",
    "cc": "2993",
    "engineCodes": "N57 D30 A",
    "KBA_Numbers": "0005ATF"
  },
  {
    "brand": "BMW",
    "model": "5 (F10)",
    "engineType": "525 d",
    "madeYear": "09.2011 - 10.2016",
    "kw": "155",
    "hp": "211",
    "cc": "1995",
    "engineCodes": "N47 D20 D",
    "KBA_Numbers": "0005BFP"
  },
  {
    "brand": "BMW",
    "model": "5 (F10)",
    "engineType": "525 d",
    "madeYear": "09.2011 - 10.2016",
    "kw": "160",
    "hp": "218",
    "cc": "1995",
    "engineCodes": "N47 D20 D",
    "KBA_Numbers": "0005BFQ"
  },
  {
    "brand": "BMW",
    "model": "5 (F10)",
    "engineType": "525 d xDrive",
    "madeYear": "09.2011 - 10.2016",
    "kw": "155",
    "hp": "211",
    "cc": "1995",
    "engineCodes": "N47 D20 D",
    "KBA_Numbers": "0005BFU"
  },
  {
    "brand": "BMW",
    "model": "5 (F10)",
    "engineType": "525 d xDrive",
    "madeYear": "09.2011 - 10.2016",
    "kw": "160",
    "hp": "218",
    "cc": "1995",
    "engineCodes": "N47 D20 D",
    "KBA_Numbers": "0005BFV"
  },
  {
    "brand": "BMW",
    "model": "5 (F10)",
    "engineType": "528 i",
    "madeYear": "03.2010 - 08.2011",
    "kw": "190",
    "hp": "258",
    "cc": "2996",
    "engineCodes": "N53 B30 A",
    "KBA_Numbers": "0005ATB"
  },
  {
    "brand": "BMW",
    "model": "5 (F10)",
    "engineType": "528 i",
    "madeYear": "09.2011 - 10.2016",
    "kw": "180",
    "hp": "245",
    "cc": "1997",
    "engineCodes": "N20 B20 A",
    "KBA_Numbers": "0005BFO"
  },
  {
    "brand": "BMW",
    "model": "5 (F10)",
    "engineType": "528 i xDrive",
    "madeYear": "09.2011 - 10.2016",
    "kw": "180",
    "hp": "245",
    "cc": "1997",
    "engineCodes": "N20 B20 A",
    "KBA_Numbers": "0005BFT"
  },
  {
    "brand": "BMW",
    "model": "5 (F10)",
    "engineType": "530 d",
    "madeYear": "01.2010 - 08.2011",
    "kw": "180",
    "hp": "245",
    "cc": "2993",
    "engineCodes": "N57 D30 A",
    "KBA_Numbers": "0005ATG"
  },
  {
    "brand": "BMW",
    "model": "5 (F10)",
    "engineType": "530 d",
    "madeYear": "09.2011 - 10.2016",
    "kw": "190",
    "hp": "258",
    "cc": "2993",
    "engineCodes": "N57 D30 A",
    "KBA_Numbers": "0005BFR"
  },
  {
    "brand": "BMW",
    "model": "5 (F10)",
    "engineType": "530 d xDrive",
    "madeYear": "03.2011 - 10.2016",
    "kw": "190",
    "hp": "258",
    "cc": "2993",
    "engineCodes": "N57 D30 A",
    "KBA_Numbers": "0005BAG"
  },
  {
    "brand": "BMW",
    "model": "5 (F10)",
    "engineType": "530 i",
    "madeYear": "03.2010 - 06.2013",
    "kw": "190",
    "hp": "258",
    "cc": "2996",
    "engineCodes": "N52 B30 AF  N52 B30 BF  N52 B30 A",
    "KBA_Numbers": "0005ATB"
  },
  {
    "brand": "BMW",
    "model": "5 (F10)",
    "engineType": "530 i",
    "madeYear": "05.2011 - 06.2013",
    "kw": "200",
    "hp": "272",
    "cc": "2996",
    "engineCodes": "N53 B30 A",
    "KBA_Numbers": "0005BFX"
  },
  {
    "brand": "BMW",
    "model": "5 (F10)",
    "engineType": "550 i xDrive",
    "madeYear": "08.2010 - 06.2013",
    "kw": "300",
    "hp": "408",
    "cc": "4395",
    "engineCodes": "N63 B44 A",
    "KBA_Numbers": "0005AYY  0005AZD"
  },
  {
    "brand": "BMW",
    "model": "5 Gran Turismo (F07)",
    "engineType": "550 i",
    "madeYear": "07.2012 - 02.2017",
    "kw": "330",
    "hp": "449",
    "cc": "4395",
    "engineCodes": "N63 B44 A  N63 B44 B",
    "KBA_Numbers": "0005BJO  0005BJP"
  },
  {
    "brand": "BMW",
    "model": "5 Gran Turismo (F07)",
    "engineType": "550 i xDrive",
    "madeYear": "06.2010 - 06.2012",
    "kw": "300",
    "hp": "408",
    "cc": "4395",
    "engineCodes": "N63 B44 A",
    "KBA_Numbers": "0005AYY  0005BAR"
  },
  {
    "brand": "BMW",
    "model": "5 Gran Turismo (F07)",
    "engineType": "550 i xDrive",
    "madeYear": "07.2012 - 02.2017",
    "kw": "330",
    "hp": "449",
    "cc": "4395",
    "engineCodes": "N63 B44 B",
    "KBA_Numbers": "0005BJY  0005BJZ"
  },
  {
    "brand": "BMW",
    "model": "5 Touring (F11)",
    "engineType": "518 d",
    "madeYear": "07.2013 - 02.2017",
    "kw": "100",
    "hp": "136",
    "cc": "1995",
    "engineCodes": "B47 D20 A  N47 D20 C",
    "KBA_Numbers": "0005BPT"
  },
  {
    "brand": "BMW",
    "model": "5 Touring (F11)",
    "engineType": "518 d",
    "madeYear": "07.2013 - 06.2014",
    "kw": "105",
    "hp": "143",
    "cc": "1995",
    "engineCodes": "N47 D20 C",
    "KBA_Numbers": "0005BPU"
  },
  {
    "brand": "BMW",
    "model": "5 Touring (F11)",
    "engineType": "518 d",
    "madeYear": "07.2014 - 02.2017",
    "kw": "110",
    "hp": "150",
    "cc": "1995",
    "engineCodes": "B47 D20 A",
    "KBA_Numbers": "0005BWR"
  },
  {
    "brand": "BMW",
    "model": "5 Touring (F11)",
    "engineType": "518 d",
    "madeYear": "07.2014 - 02.2017",
    "kw": "120",
    "hp": "163",
    "cc": "1995",
    "engineCodes": "B47 D20 A",
    "KBA_Numbers": ""
  },
  {
    "brand": "BMW",
    "model": "5 Touring (F11)",
    "engineType": "520 d",
    "madeYear": "06.2010 - 06.2014",
    "kw": "100",
    "hp": "136",
    "cc": "1995",
    "engineCodes": "N47 D20 C",
    "KBA_Numbers": ""
  },
  {
    "brand": "BMW",
    "model": "5 Touring (F11)",
    "engineType": "520 d",
    "madeYear": "06.2010 - 02.2017",
    "kw": "120",
    "hp": "163",
    "cc": "1995",
    "engineCodes": "N47 D20 C  B47 D20 A",
    "KBA_Numbers": "0005AZN"
  },
  {
    "brand": "BMW",
    "model": "5 Touring (F11)",
    "engineType": "520 d",
    "madeYear": "06.2010 - 06.2014",
    "kw": "135",
    "hp": "184",
    "cc": "1995",
    "engineCodes": "N47 D20 C",
    "KBA_Numbers": "0005AYT  0005BAB"
  },
  {
    "brand": "BMW",
    "model": "5 Touring (F11)",
    "engineType": "520 d",
    "madeYear": "06.2010 - 06.2014",
    "kw": "147",
    "hp": "200",
    "cc": "1995",
    "engineCodes": "N47 D20 C",
    "KBA_Numbers": "0005BHL"
  },
  {
    "brand": "BMW",
    "model": "5 Touring (F11)",
    "engineType": "520 d",
    "madeYear": "07.2014 - 02.2017",
    "kw": "140",
    "hp": "190",
    "cc": "1995",
    "engineCodes": "B47 D20 A",
    "KBA_Numbers": "0005BWS"
  },
  {
    "brand": "BMW",
    "model": "5 Touring (F11)",
    "engineType": "520 d",
    "madeYear": "07.2014 - 02.2017",
    "kw": "151",
    "hp": "205",
    "cc": "1995",
    "engineCodes": "B47 D20 A",
    "KBA_Numbers": "0005BZO"
  },
  {
    "brand": "BMW",
    "model": "5 Touring (F11)",
    "engineType": "520 d",
    "madeYear": "07.2014 - 02.2017",
    "kw": "155",
    "hp": "211",
    "cc": "1995",
    "engineCodes": "B47 D20 A",
    "KBA_Numbers": ""
  },
  {
    "brand": "BMW",
    "model": "5 Touring (F11)",
    "engineType": "520 d xDrive",
    "madeYear": "07.2013 - 06.2014",
    "kw": "100",
    "hp": "136",
    "cc": "1995",
    "engineCodes": "N47 D20 C",
    "KBA_Numbers": ""
  },
  {
    "brand": "BMW",
    "model": "5 Touring (F11)",
    "engineType": "520 d xDrive",
    "madeYear": "07.2013 - 02.2017",
    "kw": "120",
    "hp": "163",
    "cc": "1995",
    "engineCodes": "B47 D20 A  N47 D20 C",
    "KBA_Numbers": "0005BPV"
  },
  {
    "brand": "BMW",
    "model": "5 Touring (F11)",
    "engineType": "520 d xDrive",
    "madeYear": "07.2013 - 06.2014",
    "kw": "135",
    "hp": "184",
    "cc": "1995",
    "engineCodes": "N47 D20 C",
    "KBA_Numbers": "0005BPW"
  },
  {
    "brand": "BMW",
    "model": "5 Touring (F11)",
    "engineType": "520 d xDrive",
    "madeYear": "07.2013 - 06.2014",
    "kw": "147",
    "hp": "200",
    "cc": "1995",
    "engineCodes": "N47 D20 C",
    "KBA_Numbers": "0005BPX"
  },
  {
    "brand": "BMW",
    "model": "5 Touring (F11)",
    "engineType": "520 d xDrive",
    "madeYear": "07.2014 - 02.2017",
    "kw": "140",
    "hp": "190",
    "cc": "1995",
    "engineCodes": "B47 D20 A",
    "KBA_Numbers": "0005BWT"
  },
  {
    "brand": "BMW",
    "model": "5 Touring (F11)",
    "engineType": "520 d xDrive",
    "madeYear": "07.2014 - 02.2017",
    "kw": "151",
    "hp": "205",
    "cc": "1995",
    "engineCodes": "B47 D20 A",
    "KBA_Numbers": "0005BZP"
  },
  {
    "brand": "BMW",
    "model": "5 Touring (F11)",
    "engineType": "520 d xDrive",
    "madeYear": "07.2014 - 02.2017",
    "kw": "155",
    "hp": "211",
    "cc": "1995",
    "engineCodes": "B47 D20 A",
    "KBA_Numbers": ""
  },
  {
    "brand": "BMW",
    "model": "5 Touring (F11)",
    "engineType": "520 i",
    "madeYear": "10.2010 - 02.2017",
    "kw": "135",
    "hp": "184",
    "cc": "1997",
    "engineCodes": "N20 B20 B  N20 B20 A",
    "KBA_Numbers": "0005BFZ"
  },
  {
    "brand": "BMW",
    "model": "5 Touring (F11)",
    "engineType": "520 i",
    "madeYear": "09.2011 - 02.2017",
    "kw": "120",
    "hp": "163",
    "cc": "1997",
    "engineCodes": "N20 B20 B  N20 B20 A",
    "KBA_Numbers": "0005BFY"
  },
  {
    "brand": "BMW",
    "model": "5 Touring (F11)",
    "engineType": "523 i",
    "madeYear": "11.2009 - 08.2011",
    "kw": "150",
    "hp": "204",
    "cc": "2996",
    "engineCodes": "N53 B30 A",
    "KBA_Numbers": "0005BAQ"
  },
  {
    "brand": "BMW",
    "model": "5 Touring (F11)",
    "engineType": "523 i",
    "madeYear": "11.2009 - 08.2011",
    "kw": "150",
    "hp": "204",
    "cc": "2497",
    "engineCodes": "N52 B25 B  N52 B25 AF  N52 B25 A",
    "KBA_Numbers": "0005AYW"
  },
  {
    "brand": "BMW",
    "model": "5 Touring (F11)",
    "engineType": "525 d",
    "madeYear": "09.2010 - 08.2011",
    "kw": "150",
    "hp": "204",
    "cc": "2993",
    "engineCodes": "N57 D30 A",
    "KBA_Numbers": "0005AZP"
  },
  {
    "brand": "BMW",
    "model": "5 Touring (F11)",
    "engineType": "525 d",
    "madeYear": "09.2011 - 02.2017",
    "kw": "155",
    "hp": "211",
    "cc": "1995",
    "engineCodes": "N47 D20 D",
    "KBA_Numbers": "0005BGB"
  },
  {
    "brand": "BMW",
    "model": "5 Touring (F11)",
    "engineType": "525 d",
    "madeYear": "09.2011 - 02.2017",
    "kw": "160",
    "hp": "218",
    "cc": "1995",
    "engineCodes": "N47 D20 D",
    "KBA_Numbers": "0005BHR  0005BGC"
  },
  {
    "brand": "BMW",
    "model": "5 Touring (F11)",
    "engineType": "525 d xDrive",
    "madeYear": "07.2013 - 02.2017",
    "kw": "155",
    "hp": "211",
    "cc": "1995",
    "engineCodes": "N47 D20 D",
    "KBA_Numbers": "0005BGG"
  },
  {
    "brand": "BMW",
    "model": "5 Touring (F11)",
    "engineType": "525 d xDrive",
    "madeYear": "07.2013 - 02.2017",
    "kw": "160",
    "hp": "218",
    "cc": "1995",
    "engineCodes": "N47 D20 D",
    "KBA_Numbers": "0005BGH  0005BHT"
  },
  {
    "brand": "BMW",
    "model": "5 Touring (F11)",
    "engineType": "528 i",
    "madeYear": "11.2009 - 08.2011",
    "kw": "190",
    "hp": "258",
    "cc": "2996",
    "engineCodes": "N53 B30 A",
    "KBA_Numbers": "0005AZO"
  },
  {
    "brand": "BMW",
    "model": "5 Touring (F11)",
    "engineType": "528 i",
    "madeYear": "09.2011 - 02.2017",
    "kw": "180",
    "hp": "245",
    "cc": "1997",
    "engineCodes": "N20 B20 A",
    "KBA_Numbers": "0005BGA"
  },
  {
    "brand": "BMW",
    "model": "5 Touring (F11)",
    "engineType": "528 i xDrive",
    "madeYear": "09.2011 - 02.2017",
    "kw": "180",
    "hp": "245",
    "cc": "1997",
    "engineCodes": "N20 B20 A",
    "KBA_Numbers": "0005BGF"
  },
  {
    "brand": "BMW",
    "model": "5 Touring (F11)",
    "engineType": "530 d",
    "madeYear": "09.2011 - 02.2017",
    "kw": "190",
    "hp": "258",
    "cc": "2993",
    "engineCodes": "N57 D30 A",
    "KBA_Numbers": "0005BGD"
  },
  {
    "brand": "BMW",
    "model": "5 Touring (F11)",
    "engineType": "530 d xDrive",
    "madeYear": "03.2011 - 02.2017",
    "kw": "190",
    "hp": "258",
    "cc": "2993",
    "engineCodes": "N57 D30 A",
    "KBA_Numbers": "0005BAI"
  },
  {
    "brand": "BMW",
    "model": "5 Touring (F11)",
    "engineType": "530 i",
    "madeYear": "03.2010 - 05.2013",
    "kw": "190",
    "hp": "258",
    "cc": "2996",
    "engineCodes": "N52 B30 AF  N52 B30 A",
    "KBA_Numbers": "0005AZO"
  },
  {
    "brand": "BMW",
    "model": "5 Touring (F11)",
    "engineType": "530 i",
    "madeYear": "07.2011 - 06.2013",
    "kw": "200",
    "hp": "272",
    "cc": "2996",
    "engineCodes": "N53 B30 A",
    "KBA_Numbers": "0005BGJ"
  },
  {
    "brand": "BMW",
    "model": "5 Touring (F11)",
    "engineType": "550 i",
    "madeYear": "09.2010 - 06.2013",
    "kw": "300",
    "hp": "408",
    "cc": "4395",
    "engineCodes": "N63 B44 A",
    "KBA_Numbers": "0005BAJ"
  }
]