{
  "reference": "P 06 052",
  "id": "P 06 052",
  "name": "Fren balata seti, diskli fren PRIME LINE",
  "brand": "BREMBO",
  "wvaNumbers": [
    "24290",
    "24289",
    "D1309 8424"
  ],
  "brand_oe_map": {
    "BMW": [
      "34216778327"
    ],
    "MINI": [
      "2289155",
      "34212289155",
      "34216772894",
      "34216778325",
      "34216778326",
      "34216778327",
      "34216794059",
      "6772894",
      "6778325",
      "6778326",
      "6794059"
    ]
  },
  "eanNumber": "8020584060001",
  "pad_attributes": {
    "width1": "95",
    "width2": null,
    "height1": "39",
    "height2": "49",
    "thickness1": "17",
    "thickness2": null,
    "manufacturerRestriction": "",
    "checkmark": "",
    "SVHC": ""
  }
}