{
  "yvNo": "21179205",
  "id": "180788",
  "Brand_Reference": "180788",
  "crossNumbers": [
    {
      "maker": "ATE",
      "crossNumber": "13.0460-4041.2"
    },
    {
      "maker": "ATE",
      "crossNumber": "604041"
    },
    {
      "maker": "BENDIX-ROULUNDS",
      "crossNumber": "510116"
    },
    {
      "maker": "BOSCH",
      "crossNumber": "0 986 461 130"
    },
    {
      "maker": "BOSCH",
      "crossNumber": "0 986 561 130"
    },
    {
      "maker": "BREMBO",
      "crossNumber": "P 61 034"
    },
    {
      "maker": "DELPHI LOCKHEED",
      "crossNumber": "LP652"
    },
    {
      "maker": "FERODO",
      "crossNumber": "FDB745"
    },
    {
      "maker": "FMSI",
      "crossNumber": "D2259-9497"
    },
    {
      "maker": "GIRLING",
      "crossNumber": "6109062"
    },
    {
      "maker": "HELLA-PAGID",
      "crossNumber": "T1090"
    },
    {
      "maker": "MINTEX",
      "crossNumber": "MDB1483"
    },
    {
      "maker": "NECTO",
      "crossNumber": "FD6369A"
    },
    {
      "maker": "ROAD HOUSE",
      "crossNumber": "2247.14"
    },
    {
      "maker": "TEXTAR",
      "crossNumber": "21179 168 0 5 T406"
    },
    {
      "maker": "TEXTAR",
      "crossNumber": "2117902"
    },
    {
      "maker": "TRW",
      "crossNumber": "GDB906"
    },
    {
      "maker": "VALEO",
      "crossNumber": "598030"
    },
    {
      "maker": "WVA",
      "crossNumber": "21179"
    },
    {
      "maker": "WVA",
      "crossNumber": "21289"
    }
  ]
}