[
  {
    "brand": "TOYOTA",
    "model": "4 RUNNER IV (_N21_) | HILUX SURF",
    "engineType": "4.7 4WD (UZN215)",
    "madeYear": "01.2005 - 12.2009",
    "kw": "194",
    "hp": "264",
    "cc": "4663",
    "engineCodes": "2UZ-FE",
    "KBA_Numbers": ""
  },
  {
    "brand": "TOYOTA",
    "model": "LAND CRUISER PRADO (_J12_)",
    "engineType": "2.7 (TRJ120, TRJ125)",
    "madeYear": "11.2003 - 02.2010",
    "kw": "120",
    "hp": "163",
    "cc": "2694",
    "engineCodes": "2TR-FE",
    "KBA_Numbers": ""
  },
  {
    "brand": "TOYOTA",
    "model": "LAND CRUISER PRADO (_J12_)",
    "engineType": "3.0 D (KZJ120)",
    "madeYear": "09.2002 - 07.2009",
    "kw": "92",
    "hp": "125",
    "cc": "2982",
    "engineCodes": "1KZ-TE",
    "KBA_Numbers": ""
  },
  {
    "brand": "TOYOTA",
    "model": "LAND CRUISER PRADO (_J12_)",
    "engineType": "3.0 D (LJ120, LJ125)",
    "madeYear": "09.2002 - 02.2010",
    "kw": "70",
    "hp": "95",
    "cc": "2986",
    "engineCodes": "5L-E",
    "KBA_Numbers": ""
  },
  {
    "brand": "TOYOTA",
    "model": "LAND CRUISER PRADO (_J12_)",
    "engineType": "3.0 D-4D (KDJ120, KDJ125)",
    "madeYear": "09.2002 - 08.2009",
    "kw": "120",
    "hp": "163",
    "cc": "2982",
    "engineCodes": "1KD-FTV",
    "KBA_Numbers": "5048013"
  },
  {
    "brand": "TOYOTA",
    "model": "LAND CRUISER PRADO (_J12_)",
    "engineType": "3.0 D-4D (KDJ120, KDJ125)",
    "madeYear": "07.2004 - 08.2009",
    "kw": "122",
    "hp": "166",
    "cc": "2982",
    "engineCodes": "1KD-FTV",
    "KBA_Numbers": "5048096"
  },
  {
    "brand": "TOYOTA",
    "model": "LAND CRUISER PRADO (_J12_)",
    "engineType": "3.0 D-4D (KDJ120, KDJ125, KDJ121)",
    "madeYear": "09.2002 - 12.2010",
    "kw": "127",
    "hp": "173",
    "cc": "2982",
    "engineCodes": "1KD-FTV",
    "KBA_Numbers": "5013ACX  5013ACW"
  },
  {
    "brand": "TOYOTA",
    "model": "LAND CRUISER PRADO (_J12_)",
    "engineType": "3.0 D-4D (KDJ120_)",
    "madeYear": "08.2006 - 07.2009",
    "kw": "150",
    "hp": "204",
    "cc": "2982",
    "engineCodes": "1KD-FTV",
    "KBA_Numbers": ""
  },
  {
    "brand": "TOYOTA",
    "model": "LAND CRUISER PRADO (_J12_)",
    "engineType": "4.0 (GRJ120)",
    "madeYear": "09.2002 - 08.2010",
    "kw": "179",
    "hp": "243",
    "cc": "3956",
    "engineCodes": "1GR-FE",
    "KBA_Numbers": ""
  },
  {
    "brand": "TOYOTA",
    "model": "LAND CRUISER PRADO (_J12_)",
    "engineType": "4.0 (GRJ120, GRJ125, GRJ121)",
    "madeYear": "12.2002 - 12.2010",
    "kw": "183",
    "hp": "249",
    "cc": "3956",
    "engineCodes": "1GR-FE",
    "KBA_Numbers": "5048071  5013ACY  5013ACV"
  },
  {
    "brand": "TOYOTA",
    "model": "LAND CRUISER PRADO (_J12_)",
    "engineType": "4.0 V6 VVT-i (GRJ125)",
    "madeYear": "01.2003 - 07.2009",
    "kw": "207",
    "hp": "282",
    "cc": "3956",
    "engineCodes": "1GR-FE",
    "KBA_Numbers": ""
  }
]