{
  "reference": "78BD2236-1",
  "id": "78BD2236-1",
  "name": "Fren diski",
  "brand": "ICER",
  "wvaNumbers": [],
  "brand_oe_map": {
    "RENAULT": [
      "77 01 472 838",
      "77 01 713 008",
      "82 00 367 094"
    ]
  },
  "eanNumber": "8424073143778",
  "attributes": {
    "Type": [
      "dolu"
    ],
    "ThicknessValues": [
      "8,5"
    ],
    "MinimumThicknessValues": [
      "8,5"
    ],
    "Surface": [],
    "HeightValues": [
      "82"
    ],
    "InnerDiameter": [],
    "OuterDiameter": [
      "274"
    ],
    "BoltHoleCircle": [
      "108"
    ],
    "NumberOfHoles": [
      "5"
    ],
    "AxleVersion": [
      "Rear"
    ],
    "TechnicalInformationNumber": [
      "78BD2236-1"
    ],
    "TestMark": [
      "E1 90R-02C0527/1459, E1 90R-02C0559/0094"
    ],
    "Diameter": [
      "62"
    ],
    "Thickness": [
      "11"
    ],
    "SupplementaryInfo": [
      "Entegre edilmiş manyetik sensör halkasına sahip"
    ],
    "CenteringDiameter": [
      "62"
    ],
    "HoleArrangement_HoleNumber": [
      "5"
    ],
    "WheelBoltBoreDiameter": [],
    "Machining": [],
    "TighteningTorque": [],
    "Weight": [
      "7.534"
    ],
    "Color": [],
    "ThreadSize": []
  }
}