[
  {
    "brand": "TOYOTA",
    "model": "CALDINA Estate (_T19_)",
    "engineType": "1.8 (ST190_, ST190G)",
    "madeYear": "11.1992 - 01.1996",
    "kw": "92",
    "hp": "125",
    "cc": "1838",
    "engineCodes": "4S-FE",
    "KBA_Numbers": ""
  },
  {
    "brand": "TOYOTA",
    "model": "CALDINA Estate (_T19_)",
    "engineType": "2.0 (ST191_, ST191G)",
    "madeYear": "to 02.1995",
    "kw": "103",
    "hp": "140",
    "cc": "1998",
    "engineCodes": "3S-FE",
    "KBA_Numbers": ""
  },
  {
    "brand": "TOYOTA",
    "model": "CALDINA Estate (_T19_)",
    "engineType": "2.0 4WD (ST195_, ST195G)",
    "madeYear": "11.1992 - 08.1997",
    "kw": "99",
    "hp": "135",
    "cc": "1998",
    "engineCodes": "3S-FE",
    "KBA_Numbers": ""
  },
  {
    "brand": "TOYOTA",
    "model": "CALDINA Estate (_T19_)",
    "engineType": "2.0 TD (CT190)",
    "madeYear": "06.1994 - 09.1997",
    "kw": "56",
    "hp": "76",
    "cc": "1974",
    "engineCodes": "2C",
    "KBA_Numbers": ""
  },
  {
    "brand": "TOYOTA",
    "model": "CALDINA Estate (_T19_)",
    "engineType": "2.0 TD (CT190_, CT190G)",
    "madeYear": "01.1996 - 08.1997",
    "kw": "65",
    "hp": "88",
    "cc": "1974",
    "engineCodes": "2C-T",
    "KBA_Numbers": ""
  },
  {
    "brand": "TOYOTA",
    "model": "CALDINA Estate (_T19_)",
    "engineType": "2.0 TD (CT190G)",
    "madeYear": "06.1994 - 09.1997",
    "kw": "54",
    "hp": "73",
    "cc": "1974",
    "engineCodes": "2C",
    "KBA_Numbers": ""
  },
  {
    "brand": "TOYOTA",
    "model": "CALDINA Estate (_T21_)",
    "engineType": "1.8 (AT211G)",
    "madeYear": "10.1997 - 08.2002",
    "kw": "85",
    "hp": "116",
    "cc": "1762",
    "engineCodes": "7A-FE",
    "KBA_Numbers": ""
  },
  {
    "brand": "TOYOTA",
    "model": "CALDINA Estate (_T21_)",
    "engineType": "2.2 TD 4WD (CT216_, CT216G)",
    "madeYear": "08.1997 - 09.2002",
    "kw": "69",
    "hp": "94",
    "cc": "2184",
    "engineCodes": "3C-TE",
    "KBA_Numbers": ""
  },
  {
    "brand": "TOYOTA",
    "model": "CAMRY (_V1_) | SCEPTER",
    "engineType": "2.2 (SDV10, SXV10)",
    "madeYear": "02.1993 - 08.1997",
    "kw": "93",
    "hp": "126",
    "cc": "2164",
    "engineCodes": "5S-FE",
    "KBA_Numbers": ""
  },
  {
    "brand": "TOYOTA",
    "model": "CAMRY (_V1_) | SCEPTER",
    "engineType": "2.2 (SXV10_, SXV10R)",
    "madeYear": "06.1991 - 07.1996",
    "kw": "100",
    "hp": "136",
    "cc": "2164",
    "engineCodes": "5S-FE",
    "KBA_Numbers": "7104237"
  },
  {
    "brand": "TOYOTA",
    "model": "CAMRY (_V1_) | SCEPTER",
    "engineType": "2.2 TD (CV40)",
    "madeYear": "06.1994 - 06.1998",
    "kw": "67",
    "hp": "91",
    "cc": "2184",
    "engineCodes": "3C-T",
    "KBA_Numbers": ""
  },
  {
    "brand": "TOYOTA",
    "model": "CAMRY (_V2_)",
    "engineType": "2.2 (SXV20)",
    "madeYear": "08.1997 - 09.2002",
    "kw": "93",
    "hp": "126",
    "cc": "2164",
    "engineCodes": "5S-FE",
    "KBA_Numbers": "5013447"
  },
  {
    "brand": "TOYOTA",
    "model": "CAMRY (_V2_)",
    "engineType": "2.2 (SXV20_, SXV20)",
    "madeYear": "08.1996 - 11.2001",
    "kw": "96",
    "hp": "131",
    "cc": "2164",
    "engineCodes": "5S-FE",
    "KBA_Numbers": "5013353"
  },
  {
    "brand": "TOYOTA",
    "model": "CAMRY Estate (_V1_) | SCEPTER",
    "engineType": "2.2 (SXV10_, SXV10R)",
    "madeYear": "09.1991 - 07.1996",
    "kw": "100",
    "hp": "136",
    "cc": "2164",
    "engineCodes": "5S-FE",
    "KBA_Numbers": "1159300"
  },
  {
    "brand": "TOYOTA",
    "model": "CAMRY Estate (_V1_) | SCEPTER",
    "engineType": "3.0 (VCV10_, VCV10R)",
    "madeYear": "09.1991 - 07.1996",
    "kw": "138",
    "hp": "188",
    "cc": "2959",
    "engineCodes": "3VZ-FE",
    "KBA_Numbers": "1159301"
  },
  {
    "brand": "TOYOTA",
    "model": "CARINA E VI (_T19_)",
    "engineType": "1.6 (AT190)",
    "madeYear": "12.1993 - 09.1997",
    "kw": "73",
    "hp": "99",
    "cc": "1587",
    "engineCodes": "4A-FE",
    "KBA_Numbers": "5013327  2130306"
  },
  {
    "brand": "TOYOTA",
    "model": "CARINA E VI (_T19_)",
    "engineType": "1.6 (AT190)",
    "madeYear": "12.1993 - 09.1997",
    "kw": "85",
    "hp": "116",
    "cc": "1587",
    "engineCodes": "4A-FE",
    "KBA_Numbers": "5013326"
  },
  {
    "brand": "TOYOTA",
    "model": "CARINA E VI (_T19_)",
    "engineType": "1.6 16V (AT190_, AT190R)",
    "madeYear": "10.1995 - 09.1997",
    "kw": "78",
    "hp": "106",
    "cc": "1587",
    "engineCodes": "4A-FE",
    "KBA_Numbers": "5013338"
  },
  {
    "brand": "TOYOTA",
    "model": "CARINA E VI (_T19_)",
    "engineType": "1.6 GLI (AT190)",
    "madeYear": "04.1992 - 09.1997",
    "kw": "79",
    "hp": "107",
    "cc": "1587",
    "engineCodes": "4A-FE",
    "KBA_Numbers": "7104242  2130302"
  },
  {
    "brand": "TOYOTA",
    "model": "CARINA E VI (_T19_)",
    "engineType": "1.8 (AT191)",
    "madeYear": "01.1995 - 09.1997",
    "kw": "79",
    "hp": "107",
    "cc": "1762",
    "engineCodes": "7A-FE",
    "KBA_Numbers": "5013329  2130307"
  },
  {
    "brand": "TOYOTA",
    "model": "CARINA E VI (_T19_)",
    "engineType": "1.8 GL (AT191)",
    "madeYear": "10.1994 - 09.1997",
    "kw": "92",
    "hp": "125",
    "cc": "1762",
    "engineCodes": "7A-FE",
    "KBA_Numbers": ""
  },
  {
    "brand": "TOYOTA",
    "model": "CARINA E VI (_T19_)",
    "engineType": "2.0 D (CT190)",
    "madeYear": "04.1992 - 01.1996",
    "kw": "54",
    "hp": "73",
    "cc": "1974",
    "engineCodes": "2C",
    "KBA_Numbers": "5013330"
  },
  {
    "brand": "TOYOTA",
    "model": "CARINA E VI (_T19_)",
    "engineType": "2.0 GLI (ST191)",
    "madeYear": "04.1992 - 09.1997",
    "kw": "98",
    "hp": "133",
    "cc": "1998",
    "engineCodes": "3S-FE",
    "KBA_Numbers": "7104244  5013328  2130303"
  },
  {
    "brand": "TOYOTA",
    "model": "CARINA E VI (_T19_)",
    "engineType": "2.0 GTi (ST191)",
    "madeYear": "04.1992 - 02.1994",
    "kw": "116",
    "hp": "158",
    "cc": "1998",
    "engineCodes": "3S-GE",
    "KBA_Numbers": "7104255"
  },
  {
    "brand": "TOYOTA",
    "model": "CARINA E VI (_T19_)",
    "engineType": "2.0 GTi 16V (ST191_, ST191R)",
    "madeYear": "03.1994 - 09.1997",
    "kw": "129",
    "hp": "175",
    "cc": "1998",
    "engineCodes": "3S-GE",
    "KBA_Numbers": "7104270"
  },
  {
    "brand": "TOYOTA",
    "model": "CARINA E VI (_T19_)",
    "engineType": "2.0 i (ST191)",
    "madeYear": "12.1993 - 09.1997",
    "kw": "93",
    "hp": "126",
    "cc": "1998",
    "engineCodes": "3S-FE",
    "KBA_Numbers": "5013339"
  },
  {
    "brand": "TOYOTA",
    "model": "CARINA E VI (_T19_)",
    "engineType": "2.0 TD (CT190)",
    "madeYear": "01.1996 - 09.1997",
    "kw": "61",
    "hp": "83",
    "cc": "1974",
    "engineCodes": "2C-T",
    "KBA_Numbers": "5013340"
  },
  {
    "brand": "TOYOTA",
    "model": "CARINA E VI Saloon (_T19_)",
    "engineType": "1.5 SG (AT192_, AT192R)",
    "madeYear": "04.1992 - 09.1997",
    "kw": "77",
    "hp": "105",
    "cc": "1498",
    "engineCodes": "5A-FE",
    "KBA_Numbers": ""
  },
  {
    "brand": "TOYOTA",
    "model": "CARINA E VI Saloon (_T19_)",
    "engineType": "1.6 (AT190)",
    "madeYear": "01.1993 - 09.1997",
    "kw": "79",
    "hp": "107",
    "cc": "1587",
    "engineCodes": "4A-FE",
    "KBA_Numbers": "7104241  2130300"
  },
  {
    "brand": "TOYOTA",
    "model": "CARINA E VI Saloon (_T19_)",
    "engineType": "1.6 (AT190)",
    "madeYear": "01.1995 - 09.1997",
    "kw": "73",
    "hp": "99",
    "cc": "1587",
    "engineCodes": "4A-FE",
    "KBA_Numbers": "5013322  2130304"
  },
  {
    "brand": "TOYOTA",
    "model": "CARINA E VI Saloon (_T19_)",
    "engineType": "1.6 (AT190)",
    "madeYear": "10.1995 - 09.1997",
    "kw": "78",
    "hp": "106",
    "cc": "1587",
    "engineCodes": "4A-FE",
    "KBA_Numbers": "5013335"
  },
  {
    "brand": "TOYOTA",
    "model": "CARINA E VI Saloon (_T19_)",
    "engineType": "1.6 16V (AT190_, AT190R)",
    "madeYear": "12.1994 - 09.1997",
    "kw": "85",
    "hp": "116",
    "cc": "1587",
    "engineCodes": "4A-FE",
    "KBA_Numbers": "5013321"
  },
  {
    "brand": "TOYOTA",
    "model": "CARINA E VI Saloon (_T19_)",
    "engineType": "1.8 GL (AT191)",
    "madeYear": "10.1994 - 09.1997",
    "kw": "92",
    "hp": "125",
    "cc": "1762",
    "engineCodes": "7A-FE",
    "KBA_Numbers": ""
  },
  {
    "brand": "TOYOTA",
    "model": "CARINA E VI Saloon (_T19_)",
    "engineType": "1.8 i 16V (AT191)",
    "madeYear": "01.1995 - 09.1997",
    "kw": "79",
    "hp": "107",
    "cc": "1762",
    "engineCodes": "7A-FE",
    "KBA_Numbers": "5013324  2130305"
  },
  {
    "brand": "TOYOTA",
    "model": "CARINA E VI Saloon (_T19_)",
    "engineType": "2.0 (ST191)",
    "madeYear": "01.1993 - 09.1997",
    "kw": "98",
    "hp": "133",
    "cc": "1998",
    "engineCodes": "3S-FE",
    "KBA_Numbers": "7104243  5013323  2130301"
  },
  {
    "brand": "TOYOTA",
    "model": "CARINA E VI Saloon (_T19_)",
    "engineType": "2.0 D (CT190)",
    "madeYear": "08.1992 - 01.1996",
    "kw": "54",
    "hp": "73",
    "cc": "1974",
    "engineCodes": "2C",
    "KBA_Numbers": "5013325"
  },
  {
    "brand": "TOYOTA",
    "model": "CARINA E VI Saloon (_T19_)",
    "engineType": "2.0 GTi (ST191_, ST191R)",
    "madeYear": "04.1992 - 12.1995",
    "kw": "116",
    "hp": "158",
    "cc": "1998",
    "engineCodes": "3S-GE",
    "KBA_Numbers": "7104254"
  },
  {
    "brand": "TOYOTA",
    "model": "CARINA E VI Saloon (_T19_)",
    "engineType": "2.0 GTi 16V (ST191_, ST191R)",
    "madeYear": "03.1994 - 09.1997",
    "kw": "129",
    "hp": "175",
    "cc": "1998",
    "engineCodes": "3S-GE",
    "KBA_Numbers": "7104269"
  },
  {
    "brand": "TOYOTA",
    "model": "CARINA E VI Saloon (_T19_)",
    "engineType": "2.0 i (ST191)",
    "madeYear": "12.1992 - 09.1997",
    "kw": "93",
    "hp": "126",
    "cc": "1998",
    "engineCodes": "3S-FE",
    "KBA_Numbers": "5013336"
  },
  {
    "brand": "TOYOTA",
    "model": "CARINA E VI Saloon (_T19_)",
    "engineType": "2.0 TD (CT190_, CT190R)",
    "madeYear": "01.1996 - 09.1997",
    "kw": "61",
    "hp": "83",
    "cc": "1974",
    "engineCodes": "2C-T",
    "KBA_Numbers": "5013337"
  },
  {
    "brand": "TOYOTA",
    "model": "CARINA E VI Sportswagon (_T19_)",
    "engineType": "1.6 (AT190)",
    "madeYear": "04.1992 - 09.1997",
    "kw": "85",
    "hp": "115",
    "cc": "1587",
    "engineCodes": "4A-FE",
    "KBA_Numbers": ""
  },
  {
    "brand": "TOYOTA",
    "model": "CARINA E VI Sportswagon (_T19_)",
    "engineType": "1.6 GLI (AT190_, AT190R)",
    "madeYear": "01.1993 - 09.1997",
    "kw": "79",
    "hp": "107",
    "cc": "1587",
    "engineCodes": "4A-FE",
    "KBA_Numbers": "7104257"
  },
  {
    "brand": "TOYOTA",
    "model": "CARINA E VI Sportswagon (_T19_)",
    "engineType": "1.6 i (AT190_, AT190R)",
    "madeYear": "02.1995 - 09.1997",
    "kw": "73",
    "hp": "99",
    "cc": "1587",
    "engineCodes": "4A-FE",
    "KBA_Numbers": "7104274  5013331  2130309"
  },
  {
    "brand": "TOYOTA",
    "model": "CARINA E VI Sportswagon (_T19_)",
    "engineType": "1.8 GL (AT191)",
    "madeYear": "10.1994 - 09.1997",
    "kw": "92",
    "hp": "125",
    "cc": "1762",
    "engineCodes": "7A-FE",
    "KBA_Numbers": ""
  },
  {
    "brand": "TOYOTA",
    "model": "CARINA E VI Sportswagon (_T19_)",
    "engineType": "1.8 i (AT191_, AT191R)",
    "madeYear": "02.1995 - 09.1997",
    "kw": "79",
    "hp": "107",
    "cc": "1762",
    "engineCodes": "7A-FE",
    "KBA_Numbers": "7104275  5013333  2130310"
  },
  {
    "brand": "TOYOTA",
    "model": "CARINA E VI Sportswagon (_T19_)",
    "engineType": "2.0 D (CT190_, CT190R)",
    "madeYear": "01.1993 - 09.1997",
    "kw": "54",
    "hp": "73",
    "cc": "1974",
    "engineCodes": "2C",
    "KBA_Numbers": "5013334"
  },
  {
    "brand": "TOYOTA",
    "model": "CARINA E VI Sportswagon (_T19_)",
    "engineType": "2.0 GLI (ST191_, ST191R)",
    "madeYear": "01.1993 - 09.1997",
    "kw": "98",
    "hp": "133",
    "cc": "1998",
    "engineCodes": "3S-FE",
    "KBA_Numbers": "7104258  5013332  2130308"
  },
  {
    "brand": "TOYOTA",
    "model": "CARINA E VI Sportswagon (_T19_)",
    "engineType": "2.0 i (ST191_, ST191R)",
    "madeYear": "05.1995 - 09.1997",
    "kw": "93",
    "hp": "126",
    "cc": "1998",
    "engineCodes": "3S-FE",
    "KBA_Numbers": "5013341"
  },
  {
    "brand": "TOYOTA",
    "model": "CARINA E VI Sportswagon (_T19_)",
    "engineType": "2.0 TD (CT190_, CT190R)",
    "madeYear": "01.1996 - 09.1997",
    "kw": "61",
    "hp": "83",
    "cc": "1974",
    "engineCodes": "2C-T",
    "KBA_Numbers": "5013342"
  },
  {
    "brand": "TOYOTA",
    "model": "CELICA Coupe (_T20_)",
    "engineType": "1.8 i 16V (AT200)",
    "madeYear": "11.1993 - 11.1999",
    "kw": "85",
    "hp": "116",
    "cc": "1762",
    "engineCodes": "7A-FE",
    "KBA_Numbers": "7104266  5013300"
  },
  {
    "brand": "TOYOTA",
    "model": "COROLLA (_E10_)",
    "engineType": "1.3 12V (EE100_, EE100R)",
    "madeYear": "07.1992 - 04.1997",
    "kw": "53",
    "hp": "72",
    "cc": "1296",
    "engineCodes": "2E",
    "KBA_Numbers": ""
  },
  {
    "brand": "TOYOTA",
    "model": "COROLLA (_E10_)",
    "engineType": "1.3 XLI (EE101_, EE101R)",
    "madeYear": "09.1995 - 04.1997",
    "kw": "55",
    "hp": "75",
    "cc": "1332",
    "engineCodes": "4E-FE",
    "KBA_Numbers": "7104278  5013309"
  },
  {
    "brand": "TOYOTA",
    "model": "COROLLA (_E10_)",
    "engineType": "1.3 XLI 16V (EE101)",
    "madeYear": "07.1992 - 09.1995",
    "kw": "65",
    "hp": "88",
    "cc": "1332",
    "engineCodes": "4E-FE",
    "KBA_Numbers": "7104245"
  },
  {
    "brand": "TOYOTA",
    "model": "COROLLA (_E10_)",
    "engineType": "1.6 (AE101)",
    "madeYear": "09.1991 - 07.1995",
    "kw": "76",
    "hp": "103",
    "cc": "1587",
    "engineCodes": "4A-FE",
    "KBA_Numbers": ""
  },
  {
    "brand": "TOYOTA",
    "model": "COROLLA (_E10_)",
    "engineType": "1.6 (AE101_, AE101R)",
    "madeYear": "05.1992 - 04.1997",
    "kw": "85",
    "hp": "115",
    "cc": "1587",
    "engineCodes": "4A-FE",
    "KBA_Numbers": ""
  },
  {
    "brand": "TOYOTA",
    "model": "COROLLA (_E10_)",
    "engineType": "1.6 (AE101_, AE101R)",
    "madeYear": "09.1994 - 12.1997",
    "kw": "78",
    "hp": "106",
    "cc": "1587",
    "engineCodes": "4A-FE  4A-F",
    "KBA_Numbers": "5013349"
  },
  {
    "brand": "TOYOTA",
    "model": "COROLLA (_E10_)",
    "engineType": "1.6 Si (AE101_, AE101R)",
    "madeYear": "09.1995 - 04.1997",
    "kw": "84",
    "hp": "114",
    "cc": "1587",
    "engineCodes": "4A-FE",
    "KBA_Numbers": "5013306"
  },
  {
    "brand": "TOYOTA",
    "model": "COROLLA (_E10_)",
    "engineType": "2.0 D (CE100_, CE100R)",
    "madeYear": "07.1992 - 04.1997",
    "kw": "53",
    "hp": "72",
    "cc": "1974",
    "engineCodes": "2C",
    "KBA_Numbers": "7104259  5013312"
  },
  {
    "brand": "TOYOTA",
    "model": "COROLLA (_E11_)",
    "engineType": "1.3 (EE111_)",
    "madeYear": "05.1997 - 09.1999",
    "kw": "63",
    "hp": "86",
    "cc": "1332",
    "engineCodes": "4E-FE",
    "KBA_Numbers": ""
  },
  {
    "brand": "TOYOTA",
    "model": "COROLLA (_E11_)",
    "engineType": "1.4 (EE111_, EE111R)",
    "madeYear": "05.1997 - 09.1999",
    "kw": "63",
    "hp": "86",
    "cc": "1332",
    "engineCodes": "4E-FE",
    "KBA_Numbers": "5013362"
  },
  {
    "brand": "TOYOTA",
    "model": "COROLLA (_E11_)",
    "engineType": "1.4 16V (ZZE111_, ZZE111R)",
    "madeYear": "02.2000 - 11.2001",
    "kw": "71",
    "hp": "97",
    "cc": "1398",
    "engineCodes": "4ZZ-FE",
    "KBA_Numbers": "5013415"
  },
  {
    "brand": "TOYOTA",
    "model": "COROLLA (_E11_)",
    "engineType": "1.6 (AE111)",
    "madeYear": "05.1995 - 02.2000",
    "kw": "81",
    "hp": "110",
    "cc": "1587",
    "engineCodes": "4A-FE",
    "KBA_Numbers": ""
  },
  {
    "brand": "TOYOTA",
    "model": "COROLLA (_E11_)",
    "engineType": "1.6 16V (ZZE112_, ZZE112R)",
    "madeYear": "08.1999 - 12.2001",
    "kw": "81",
    "hp": "110",
    "cc": "1598",
    "engineCodes": "3ZZ-FE",
    "KBA_Numbers": "5013366"
  },
  {
    "brand": "TOYOTA",
    "model": "COROLLA (_E11_)",
    "engineType": "1.6 Aut. (AE111_, AE111R)",
    "madeYear": "04.1997 - 02.2000",
    "kw": "79",
    "hp": "107",
    "cc": "1587",
    "engineCodes": "4A-FE",
    "KBA_Numbers": "5013370"
  },
  {
    "brand": "TOYOTA",
    "model": "COROLLA (_E11_)",
    "engineType": "1.8 (AE112_)",
    "madeYear": "10.1997 - 10.2001",
    "kw": "81",
    "hp": "110",
    "cc": "1762",
    "engineCodes": "7A-FE",
    "KBA_Numbers": ""
  },
  {
    "brand": "TOYOTA",
    "model": "COROLLA (_E11_)",
    "engineType": "1.9 D (WZE110_, WZE110R)",
    "madeYear": "02.2000 - 11.2001",
    "kw": "51",
    "hp": "69",
    "cc": "1867",
    "engineCodes": "1WZ",
    "KBA_Numbers": "5013419"
  },
  {
    "brand": "TOYOTA",
    "model": "COROLLA (_E11_)",
    "engineType": "2.0 D (CE110_, CE110R)",
    "madeYear": "04.1997 - 02.2000",
    "kw": "53",
    "hp": "72",
    "cc": "1975",
    "engineCodes": "2C-E",
    "KBA_Numbers": "5013374"
  },
  {
    "brand": "TOYOTA",
    "model": "COROLLA (_E11_)",
    "engineType": "2.0 D-4D (CDE110_, CDE110R)",
    "madeYear": "09.2000 - 11.2001",
    "kw": "66",
    "hp": "90",
    "cc": "1995",
    "engineCodes": "1CD-FTV",
    "KBA_Numbers": "5013442"
  },
  {
    "brand": "TOYOTA",
    "model": "COROLLA Compact (_E10_) | COROLLA SECCA",
    "engineType": "1.3 12V (EE100_, EE100R)",
    "madeYear": "07.1992 - 05.1995",
    "kw": "53",
    "hp": "72",
    "cc": "1296",
    "engineCodes": "2E",
    "KBA_Numbers": ""
  },
  {
    "brand": "TOYOTA",
    "model": "COROLLA Compact (_E10_) | COROLLA SECCA",
    "engineType": "1.3 XLI (EE101_, EE101R)",
    "madeYear": "08.1995 - 04.1997",
    "kw": "55",
    "hp": "75",
    "cc": "1332",
    "engineCodes": "4E-FE",
    "KBA_Numbers": "7104279  5013310"
  },
  {
    "brand": "TOYOTA",
    "model": "COROLLA Compact (_E10_) | COROLLA SECCA",
    "engineType": "1.3 XLI 16V (EE101)",
    "madeYear": "07.1992 - 09.1995",
    "kw": "65",
    "hp": "88",
    "cc": "1332",
    "engineCodes": "4E-FE",
    "KBA_Numbers": "7104246"
  },
  {
    "brand": "TOYOTA",
    "model": "COROLLA Compact (_E10_) | COROLLA SECCA",
    "engineType": "1.6 i (AE101)",
    "madeYear": "09.1994 - 11.1999",
    "kw": "78",
    "hp": "106",
    "cc": "1587",
    "engineCodes": "4A-FE",
    "KBA_Numbers": "5013350"
  },
  {
    "brand": "TOYOTA",
    "model": "COROLLA Compact (_E10_) | COROLLA SECCA",
    "engineType": "1.6 Si (AE101_, AE101R)",
    "madeYear": "07.1992 - 04.1997",
    "kw": "84",
    "hp": "114",
    "cc": "1587",
    "engineCodes": "4A-FE",
    "KBA_Numbers": "7104249  5013307"
  },
  {
    "brand": "TOYOTA",
    "model": "COROLLA Compact (_E10_) | COROLLA SECCA",
    "engineType": "1.8 GT (AE102_, AE102R)",
    "madeYear": "11.1992 - 05.1995",
    "kw": "86",
    "hp": "117",
    "cc": "1762",
    "engineCodes": "7A-FE",
    "KBA_Numbers": ""
  },
  {
    "brand": "TOYOTA",
    "model": "COROLLA Compact (_E10_) | COROLLA SECCA",
    "engineType": "1.8 GTi 4WD (AE103)",
    "madeYear": "05.1992 - 07.1995",
    "kw": "92",
    "hp": "125",
    "cc": "1762",
    "engineCodes": "7A-FE",
    "KBA_Numbers": ""
  },
  {
    "brand": "TOYOTA",
    "model": "COROLLA Compact (_E10_) | COROLLA SECCA",
    "engineType": "2.0 D (CE100_, CE100R)",
    "madeYear": "07.1992 - 04.1997",
    "kw": "53",
    "hp": "72",
    "cc": "1974",
    "engineCodes": "2C",
    "KBA_Numbers": "7104251  5013313"
  },
  {
    "brand": "TOYOTA",
    "model": "COROLLA Compact (_E11_)",
    "engineType": "1.4 (EE111_, EE111R)",
    "madeYear": "05.1997 - 09.1999",
    "kw": "63",
    "hp": "86",
    "cc": "1332",
    "engineCodes": "4E-FE",
    "KBA_Numbers": "5013360"
  },
  {
    "brand": "TOYOTA",
    "model": "COROLLA Compact (_E11_)",
    "engineType": "1.4 (ZZE111_, ZZE111R)",
    "madeYear": "10.1999 - 01.2002",
    "kw": "71",
    "hp": "97",
    "cc": "1398",
    "engineCodes": "4ZZ-FE",
    "KBA_Numbers": "5013417"
  },
  {
    "brand": "TOYOTA",
    "model": "COROLLA Compact (_E11_)",
    "engineType": "1.6 (AE111_)",
    "madeYear": "05.1997 - 02.2000",
    "kw": "81",
    "hp": "110",
    "cc": "1587",
    "engineCodes": "4A-FE",
    "KBA_Numbers": "5013364"
  },
  {
    "brand": "TOYOTA",
    "model": "COROLLA Compact (_E11_)",
    "engineType": "1.6 (ZZE112_, ZZE112R)",
    "madeYear": "10.1999 - 10.2001",
    "kw": "81",
    "hp": "110",
    "cc": "1598",
    "engineCodes": "3ZZ-FE",
    "KBA_Numbers": "5013364"
  },
  {
    "brand": "TOYOTA",
    "model": "COROLLA Compact (_E11_)",
    "engineType": "1.6 Aut. (AE111_, AE111R)",
    "madeYear": "05.1997 - 02.2000",
    "kw": "79",
    "hp": "107",
    "cc": "1587",
    "engineCodes": "4A-FE",
    "KBA_Numbers": "5013368"
  },
  {
    "brand": "TOYOTA",
    "model": "COROLLA Compact (_E11_)",
    "engineType": "1.9 D (WZE110_, WZE110R)",
    "madeYear": "02.2000 - 01.2002",
    "kw": "51",
    "hp": "69",
    "cc": "1867",
    "engineCodes": "1WZ",
    "KBA_Numbers": "5013423"
  },
  {
    "brand": "TOYOTA",
    "model": "COROLLA Compact (_E11_)",
    "engineType": "2.0 D (CE110_, CE110R)",
    "madeYear": "04.1997 - 02.2000",
    "kw": "53",
    "hp": "72",
    "cc": "1975",
    "engineCodes": "2C-E",
    "KBA_Numbers": "5013372"
  },
  {
    "brand": "TOYOTA",
    "model": "COROLLA Compact (_E11_)",
    "engineType": "2.0 D-4D (CDE110_, CDE110R)",
    "madeYear": "09.2000 - 01.2002",
    "kw": "66",
    "hp": "90",
    "cc": "1995",
    "engineCodes": "1CD-FTV",
    "KBA_Numbers": "5013440"
  },
  {
    "brand": "TOYOTA",
    "model": "COROLLA Estate (_E10_)",
    "engineType": "1.3 12V (EE100_, EE100R)",
    "madeYear": "07.1992 - 05.1995",
    "kw": "53",
    "hp": "72",
    "cc": "1296",
    "engineCodes": "2E",
    "KBA_Numbers": ""
  },
  {
    "brand": "TOYOTA",
    "model": "COROLLA Estate (_E10_)",
    "engineType": "1.3 XLI (EE101_, EE101R)",
    "madeYear": "09.1995 - 04.1997",
    "kw": "55",
    "hp": "75",
    "cc": "1332",
    "engineCodes": "4E-FE",
    "KBA_Numbers": "7104280  5013311"
  },
  {
    "brand": "TOYOTA",
    "model": "COROLLA Estate (_E10_)",
    "engineType": "1.3 XLI 16V (EE101_, EE101R)",
    "madeYear": "07.1992 - 09.1995",
    "kw": "65",
    "hp": "88",
    "cc": "1332",
    "engineCodes": "4E-FE",
    "KBA_Numbers": "7104248"
  },
  {
    "brand": "TOYOTA",
    "model": "COROLLA Estate (_E10_)",
    "engineType": "1.6 Si (AE101_, AE101R)",
    "madeYear": "07.1992 - 04.1997",
    "kw": "84",
    "hp": "114",
    "cc": "1587",
    "engineCodes": "4A-FE",
    "KBA_Numbers": "5013308"
  },
  {
    "brand": "TOYOTA",
    "model": "COROLLA Estate (_E10_)",
    "engineType": "1.8 16V 4WD (AE103_, AE103)",
    "madeYear": "09.1995 - 04.1997",
    "kw": "81",
    "hp": "110",
    "cc": "1762",
    "engineCodes": "7A-FE",
    "KBA_Numbers": "5013315"
  },
  {
    "brand": "TOYOTA",
    "model": "COROLLA Estate (_E10_)",
    "engineType": "2.0 D (CE100_, CE100R)",
    "madeYear": "07.1992 - 04.1997",
    "kw": "53",
    "hp": "72",
    "cc": "1974",
    "engineCodes": "2C",
    "KBA_Numbers": "7104253  5013314"
  },
  {
    "brand": "TOYOTA",
    "model": "COROLLA Estate (_E11_)",
    "engineType": "1.4 (EE111_, EE111R)",
    "madeYear": "04.1997 - 02.2000",
    "kw": "63",
    "hp": "86",
    "cc": "1332",
    "engineCodes": "4E-FE",
    "KBA_Numbers": "5013363"
  },
  {
    "brand": "TOYOTA",
    "model": "COROLLA Estate (_E11_)",
    "engineType": "1.4 16V (ZZE111_, ZZE111R)",
    "madeYear": "02.2000 - 10.2001",
    "kw": "71",
    "hp": "97",
    "cc": "1398",
    "engineCodes": "4ZZ-FE",
    "KBA_Numbers": "5013418"
  },
  {
    "brand": "TOYOTA",
    "model": "COROLLA Estate (_E11_)",
    "engineType": "1.6 (AE111_, AE111R)",
    "madeYear": "04.1997 - 02.2000",
    "kw": "81",
    "hp": "110",
    "cc": "1587",
    "engineCodes": "4A-FE",
    "KBA_Numbers": "5013367"
  },
  {
    "brand": "TOYOTA",
    "model": "COROLLA Estate (_E11_)",
    "engineType": "1.6 16V (ZZE112_, ZZE112R)",
    "madeYear": "02.2000 - 10.2001",
    "kw": "81",
    "hp": "110",
    "cc": "1598",
    "engineCodes": "3ZZ-FE",
    "KBA_Numbers": "5013367"
  },
  {
    "brand": "TOYOTA",
    "model": "COROLLA Estate (_E11_)",
    "engineType": "1.6 Aut. (AE111_, AE111R)",
    "madeYear": "04.1997 - 02.2000",
    "kw": "79",
    "hp": "107",
    "cc": "1587",
    "engineCodes": "4A-FE",
    "KBA_Numbers": "5013371"
  },
  {
    "brand": "TOYOTA",
    "model": "COROLLA Estate (_E11_)",
    "engineType": "1.8 4WD (AE115_, AE115R)",
    "madeYear": "04.1997 - 10.2001",
    "kw": "81",
    "hp": "110",
    "cc": "1762",
    "engineCodes": "7A-FE",
    "KBA_Numbers": "5013376"
  },
  {
    "brand": "TOYOTA",
    "model": "COROLLA Estate (_E11_)",
    "engineType": "1.9 D (WZE110_, WZE110R)",
    "madeYear": "02.2000 - 10.2001",
    "kw": "51",
    "hp": "69",
    "cc": "1867",
    "engineCodes": "1WZ",
    "KBA_Numbers": "5013421"
  },
  {
    "brand": "TOYOTA",
    "model": "COROLLA Estate (_E11_)",
    "engineType": "2.0 D (CE110_, CE110R)",
    "madeYear": "04.1997 - 02.2000",
    "kw": "53",
    "hp": "72",
    "cc": "1975",
    "engineCodes": "2C-E",
    "KBA_Numbers": "5013375"
  },
  {
    "brand": "TOYOTA",
    "model": "COROLLA Estate (_E11_)",
    "engineType": "2.0 D-4D (CDE110_, CDE110R)",
    "madeYear": "09.2000 - 10.2001",
    "kw": "66",
    "hp": "90",
    "cc": "1995",
    "engineCodes": "1CD-FTV",
    "KBA_Numbers": "5013443"
  },
  {
    "brand": "TOYOTA",
    "model": "COROLLA LEVIN Coupe (_E10_)",
    "engineType": "1.6 GT (AE101)",
    "madeYear": "to 05.1995",
    "kw": "85",
    "hp": "116",
    "cc": "1587",
    "engineCodes": "4A-FE",
    "KBA_Numbers": ""
  },
  {
    "brand": "TOYOTA",
    "model": "COROLLA LEVIN Coupe (_E10_)",
    "engineType": "1.6 GT-Z (AE101)",
    "madeYear": "06.1991 - 08.1997",
    "kw": "125",
    "hp": "170",
    "cc": "1587",
    "engineCodes": "4A-GZE",
    "KBA_Numbers": ""
  },
  {
    "brand": "TOYOTA",
    "model": "COROLLA Liftback (_E10_)",
    "engineType": "1.3 12V (EE100_, EE100R)",
    "madeYear": "07.1992 - 05.1995",
    "kw": "53",
    "hp": "72",
    "cc": "1296",
    "engineCodes": "2E",
    "KBA_Numbers": ""
  },
  {
    "brand": "TOYOTA",
    "model": "COROLLA Liftback (_E10_)",
    "engineType": "1.3 XLI (EE101_, EE101R)",
    "madeYear": "07.1992 - 04.1997",
    "kw": "65",
    "hp": "88",
    "cc": "1332",
    "engineCodes": "4E-FE",
    "KBA_Numbers": "7104247"
  },
  {
    "brand": "TOYOTA",
    "model": "COROLLA Liftback (_E10_)",
    "engineType": "1.6 GLI (AE101_, AE101R)",
    "madeYear": "07.1992 - 04.1997",
    "kw": "84",
    "hp": "114",
    "cc": "1587",
    "engineCodes": "4A-FE",
    "KBA_Numbers": "7104250"
  },
  {
    "brand": "TOYOTA",
    "model": "COROLLA Liftback (_E10_)",
    "engineType": "1.8 GT (AE102_, AE102R)",
    "madeYear": "11.1992 - 05.1995",
    "kw": "86",
    "hp": "117",
    "cc": "1762",
    "engineCodes": "7A-FE",
    "KBA_Numbers": ""
  },
  {
    "brand": "TOYOTA",
    "model": "COROLLA Liftback (_E10_)",
    "engineType": "2.0 D (CE100_, CE100R)",
    "madeYear": "07.1992 - 04.1997",
    "kw": "53",
    "hp": "72",
    "cc": "1974",
    "engineCodes": "2C",
    "KBA_Numbers": "7104252"
  },
  {
    "brand": "TOYOTA",
    "model": "COROLLA Liftback (_E11_)",
    "engineType": "1.4 (EE111_, EE111R)",
    "madeYear": "05.1997 - 09.1999",
    "kw": "63",
    "hp": "86",
    "cc": "1332",
    "engineCodes": "4E-FE",
    "KBA_Numbers": "5013361  5013403"
  },
  {
    "brand": "TOYOTA",
    "model": "COROLLA Liftback (_E11_)",
    "engineType": "1.4 (ZZE111_, ZZE111R)",
    "madeYear": "10.1999 - 01.2002",
    "kw": "71",
    "hp": "97",
    "cc": "1398",
    "engineCodes": "4ZZ-FE",
    "KBA_Numbers": "5013416  5013422"
  },
  {
    "brand": "TOYOTA",
    "model": "COROLLA Liftback (_E11_)",
    "engineType": "1.6 (AE111_, AE111R)",
    "madeYear": "05.1997 - 08.2001",
    "kw": "81",
    "hp": "110",
    "cc": "1587",
    "engineCodes": "4A-FE",
    "KBA_Numbers": "5013365  5013404"
  },
  {
    "brand": "TOYOTA",
    "model": "COROLLA Liftback (_E11_)",
    "engineType": "1.6 (ZZE112_, ZZE112R)",
    "madeYear": "02.2000 - 01.2002",
    "kw": "81",
    "hp": "110",
    "cc": "1598",
    "engineCodes": "3ZZ-FE",
    "KBA_Numbers": "5013365  5013404"
  },
  {
    "brand": "TOYOTA",
    "model": "COROLLA Liftback (_E11_)",
    "engineType": "1.6 Aut. (AE111_)",
    "madeYear": "05.1997 - 02.2000",
    "kw": "79",
    "hp": "107",
    "cc": "1587",
    "engineCodes": "4A-FE",
    "KBA_Numbers": "5013369  5013405"
  },
  {
    "brand": "TOYOTA",
    "model": "COROLLA Liftback (_E11_)",
    "engineType": "1.9 D (WZE110_, WZE110R)",
    "madeYear": "02.2000 - 01.2002",
    "kw": "51",
    "hp": "69",
    "cc": "1867",
    "engineCodes": "1WZ",
    "KBA_Numbers": "5013420"
  },
  {
    "brand": "TOYOTA",
    "model": "COROLLA Liftback (_E11_)",
    "engineType": "2.0 D (CE110)",
    "madeYear": "04.1997 - 02.2000",
    "kw": "53",
    "hp": "72",
    "cc": "1975",
    "engineCodes": "2C-E",
    "KBA_Numbers": "5013373"
  },
  {
    "brand": "TOYOTA",
    "model": "COROLLA Liftback (_E11_)",
    "engineType": "2.0 D-4D (CDE110_, CDE110R)",
    "madeYear": "09.2000 - 01.2002",
    "kw": "66",
    "hp": "90",
    "cc": "1995",
    "engineCodes": "1CD-FTV",
    "KBA_Numbers": "5013441"
  },
  {
    "brand": "TOYOTA",
    "model": "COROLLA Liftback (_E9_)",
    "engineType": "1.6 EFi (AE92, AE93)",
    "madeYear": "05.1992 - 04.1997",
    "kw": "85",
    "hp": "116",
    "cc": "1587",
    "engineCodes": "4A-FE",
    "KBA_Numbers": ""
  },
  {
    "brand": "TOYOTA",
    "model": "CORONA Saloon (_T19_)",
    "engineType": "1.6 (AT190)",
    "madeYear": "02.1992 - 09.1997",
    "kw": "73",
    "hp": "99",
    "cc": "1587",
    "engineCodes": "4A-FE",
    "KBA_Numbers": ""
  },
  {
    "brand": "TOYOTA",
    "model": "CORONA Saloon (_T19_)",
    "engineType": "1.8 (ST190_, ST190)",
    "madeYear": "to 12.1994",
    "kw": "92",
    "hp": "125",
    "cc": "1838",
    "engineCodes": "4S-FE",
    "KBA_Numbers": ""
  },
  {
    "brand": "TOYOTA",
    "model": "MARK II VIII Saloon (_X10_)",
    "engineType": "2.0 VVTi (GX100)",
    "madeYear": "10.1996 - 09.2001",
    "kw": "118",
    "hp": "160",
    "cc": "1988",
    "engineCodes": "1G-FE",
    "KBA_Numbers": ""
  },
  {
    "brand": "TOYOTA",
    "model": "PICNIC (_XM1_) | IPSUM",
    "engineType": "2.0 (SXM10)",
    "madeYear": "09.1996 - 05.2001",
    "kw": "99",
    "hp": "135",
    "cc": "1998",
    "engineCodes": "3S-FE",
    "KBA_Numbers": ""
  },
  {
    "brand": "TOYOTA",
    "model": "PICNIC (_XM1_) | IPSUM",
    "engineType": "2.0 (SXM10_, SXM10G)",
    "madeYear": "05.1996 - 04.2001",
    "kw": "100",
    "hp": "136",
    "cc": "1998",
    "engineCodes": "3S-FE",
    "KBA_Numbers": ""
  },
  {
    "brand": "TOYOTA",
    "model": "PICNIC (_XM1_) | IPSUM",
    "engineType": "2.0 (SXM10_, SXM10G)",
    "madeYear": "06.2000 - 12.2001",
    "kw": "90",
    "hp": "122",
    "cc": "1998",
    "engineCodes": "3S-FE",
    "KBA_Numbers": "5013430"
  },
  {
    "brand": "TOYOTA",
    "model": "PICNIC (_XM1_) | IPSUM",
    "engineType": "2.0 16V (SXM10_, SXM10G)",
    "madeYear": "08.1996 - 09.2000",
    "kw": "94",
    "hp": "128",
    "cc": "1998",
    "engineCodes": "3S-FE",
    "KBA_Numbers": "5013359"
  },
  {
    "brand": "TOYOTA",
    "model": "PICNIC (_XM1_) | IPSUM",
    "engineType": "2.0 4WD (SXM15)",
    "madeYear": "09.1996 - 05.2001",
    "kw": "99",
    "hp": "135",
    "cc": "1998",
    "engineCodes": "3S-FE",
    "KBA_Numbers": ""
  },
  {
    "brand": "TOYOTA",
    "model": "PICNIC (_XM1_) | IPSUM",
    "engineType": "2.2 D (CMX10_, CXM10G)",
    "madeYear": "08.1997 - 12.2001",
    "kw": "66",
    "hp": "90",
    "cc": "2184",
    "engineCodes": "3C-TE",
    "KBA_Numbers": "5013380"
  },
  {
    "brand": "TOYOTA",
    "model": "RAV 4 I (_A1_)",
    "engineType": "2.0",
    "madeYear": "09.1997 - 09.2000",
    "kw": "95",
    "hp": "129",
    "cc": "1998",
    "engineCodes": "3S-FE",
    "KBA_Numbers": ""
  },
  {
    "brand": "TOYOTA",
    "model": "RAV 4 I (_A1_)",
    "engineType": "2.0 4WD (SXA10, SXA11)",
    "madeYear": "06.1994 - 06.2000",
    "kw": "95",
    "hp": "129",
    "cc": "1998",
    "engineCodes": "3S-FE",
    "KBA_Numbers": "7104272  5013302"
  },
  {
    "brand": "TOYOTA",
    "model": "RAV 4 I (_A1_)",
    "engineType": "2.0 4WD (SXA10, SXA11)",
    "madeYear": "07.1996 - 06.2000",
    "kw": "94",
    "hp": "128",
    "cc": "1998",
    "engineCodes": "3S-FE",
    "KBA_Numbers": "5013358"
  },
  {
    "brand": "TOYOTA",
    "model": "RAV 4 I Cabrio (_A1_)",
    "engineType": "2.0 4WD (SXA10)",
    "madeYear": "12.1997 - 06.2000",
    "kw": "94",
    "hp": "129",
    "cc": "1998",
    "engineCodes": "3S-FE",
    "KBA_Numbers": "5013396"
  },
  {
    "brand": "TOYOTA",
    "model": "SPRINTER Saloon (_E1_)",
    "engineType": "1.6 (AE101_, AE101)",
    "madeYear": "06.1991 - 12.2000",
    "kw": "81",
    "hp": "110",
    "cc": "1587",
    "engineCodes": "4A-FE",
    "KBA_Numbers": ""
  },
  {
    "brand": "TOYOTA",
    "model": "SPRINTER Saloon (_E1_)",
    "engineType": "2.0 D (CE100, CE110)",
    "madeYear": "06.1991 - 11.2000",
    "kw": "54",
    "hp": "73",
    "cc": "1974",
    "engineCodes": "2C",
    "KBA_Numbers": ""
  },
  {
    "brand": "TOYOTA",
    "model": "VISTA Saloon (_V5_)",
    "engineType": "1.8 (ZZV50)",
    "madeYear": "06.1998 - 08.2003",
    "kw": "96",
    "hp": "131",
    "cc": "1794",
    "engineCodes": "1ZZ-FE",
    "KBA_Numbers": ""
  },
  {
    "brand": "TOYOTA",
    "model": "VISTA Saloon (_V5_)",
    "engineType": "2.0 (AZV50)",
    "madeYear": "06.1998 - 08.2003",
    "kw": "112",
    "hp": "152",
    "cc": "1998",
    "engineCodes": "1AZ-FSE",
    "KBA_Numbers": ""
  },
  {
    "brand": "TOYOTA",
    "model": "VISTA Saloon (_V5_)",
    "engineType": "2.0 (SV50)",
    "madeYear": "06.1998 - 08.2003",
    "kw": "107",
    "hp": "145",
    "cc": "1998",
    "engineCodes": "3S-FSE",
    "KBA_Numbers": ""
  }
]