{
  "reference": "DF4448",
  "id": "DF4448",
  "name": "Fren diski",
  "brand": "TRW",
  "brand_oe_map": {
    "BMW": [
      "34 21 6 764 647",
      "34 21 6 855 001",
      "6 764 647",
      "6 855 001"
    ]
  },
  "eanNumber": "3322937473601",
  "disc": {
    "Type": [
      "dolu"
    ],
    "ThicknessValues": [
      "10"
    ],
    "MinimumThicknessValues": [
      "8,4"
    ],
    "Surface": [
      "Boyalı"
    ],
    "HeightValues": [
      "65"
    ],
    "InnerDiameter": [],
    "OuterDiameter": [
      "280"
    ],
    "BoltHoleCircle": [
      "120"
    ],
    "NumberOfHoles": [
      "5"
    ],
    "AxleVersion": [],
    "TechnicalInformationNumber": [],
    "TestMark": [
      "E190R-02C0204/0525"
    ],
    "Diameter": [],
    "Thickness": [],
    "SupplementaryInfo": [],
    "CenteringDiameter": [
      "75"
    ],
    "HoleArrangement_HoleNumber": [],
    "WheelBoltBoreDiameter": [],
    "Machining": [],
    "TighteningTorque": [],
    "Weight": [],
    "Color": [
      "siyah"
    ],
    "ThreadSize": [
      "14,7"
    ]
  }
}