[
  {
    "brand": "AUDI",
    "model": "A4 B6 (8E2) | A4 / S4",
    "engineType": "S4 quattro",
    "madeYear": "03.2003 - 12.2004",
    "kw": "253",
    "hp": "344",
    "cc": "4163",
    "engineCodes": "BBK",
    "KBA_Numbers": "0588825"
  },
  {
    "brand": "AUDI",
    "model": "A4 B6 Avant (8E5) | A4 / S4",
    "engineType": "S4 quattro",
    "madeYear": "03.2003 - 12.2004",
    "kw": "253",
    "hp": "344",
    "cc": "4163",
    "engineCodes": "BBK",
    "KBA_Numbers": "0588824"
  },
  {
    "brand": "AUDI",
    "model": "A4 B6 Convertible (8H7) | A4 / S4",
    "engineType": "1.8 T",
    "madeYear": "07.2002 - 12.2005",
    "kw": "120",
    "hp": "163",
    "cc": "1781",
    "engineCodes": "BFB",
    "KBA_Numbers": "0588812  0588AEW"
  },
  {
    "brand": "AUDI",
    "model": "A4 B6 Convertible (8H7) | A4 / S4",
    "engineType": "S4 quattro",
    "madeYear": "03.2004 - 12.2005",
    "kw": "253",
    "hp": "344",
    "cc": "4163",
    "engineCodes": "BBK  BHF",
    "KBA_Numbers": "7967299  7967AAD  0588859  0588AET"
  },
  {
    "brand": "AUDI",
    "model": "A4 B7 (8EC) | A4 / S4",
    "engineType": "2.0 TDI",
    "madeYear": "06.2006 - 06.2008",
    "kw": "120",
    "hp": "163",
    "cc": "1968",
    "engineCodes": "BVA",
    "KBA_Numbers": "0588AFQ"
  },
  {
    "brand": "AUDI",
    "model": "A4 B7 (8EC) | A4 / S4",
    "engineType": "2.0 TDI",
    "madeYear": "06.2006 - 06.2008",
    "kw": "125",
    "hp": "170",
    "cc": "1968",
    "engineCodes": "BRD",
    "KBA_Numbers": "0588AFK"
  },
  {
    "brand": "AUDI",
    "model": "A4 B7 (8EC) | A4 / S4",
    "engineType": "2.0 TDI quattro",
    "madeYear": "06.2006 - 06.2008",
    "kw": "120",
    "hp": "163",
    "cc": "1968",
    "engineCodes": "BVA",
    "KBA_Numbers": "0588AFR"
  },
  {
    "brand": "AUDI",
    "model": "A4 B7 (8EC) | A4 / S4",
    "engineType": "2.0 TDI quattro",
    "madeYear": "06.2006 - 06.2008",
    "kw": "125",
    "hp": "170",
    "cc": "1968",
    "engineCodes": "BRD",
    "KBA_Numbers": "0588AFM"
  },
  {
    "brand": "AUDI",
    "model": "A4 B7 (8EC) | A4 / S4",
    "engineType": "2.0 TFSI",
    "madeYear": "11.2004 - 06.2008",
    "kw": "147",
    "hp": "200",
    "cc": "1984",
    "engineCodes": "BWE  BGB",
    "KBA_Numbers": "0588863  0588ADH"
  },
  {
    "brand": "AUDI",
    "model": "A4 B7 (8EC) | A4 / S4",
    "engineType": "2.0 TFSI",
    "madeYear": "06.2005 - 06.2008",
    "kw": "162",
    "hp": "220",
    "cc": "1984",
    "engineCodes": "BUL",
    "KBA_Numbers": "7967325  7967AAF  0588AFD"
  },
  {
    "brand": "AUDI",
    "model": "A4 B7 (8EC) | A4 / S4",
    "engineType": "2.0 TFSI",
    "madeYear": "10.2006 - 06.2008",
    "kw": "125",
    "hp": "170",
    "cc": "1984",
    "engineCodes": "BPJ  BYK",
    "KBA_Numbers": "0588AFV"
  },
  {
    "brand": "AUDI",
    "model": "A4 B7 (8EC) | A4 / S4",
    "engineType": "2.0 TFSI quattro",
    "madeYear": "11.2004 - 06.2008",
    "kw": "147",
    "hp": "200",
    "cc": "1984",
    "engineCodes": "BWE  BGB",
    "KBA_Numbers": "0588864  0588ADI"
  },
  {
    "brand": "AUDI",
    "model": "A4 B7 (8EC) | A4 / S4",
    "engineType": "2.0 TFSI quattro",
    "madeYear": "06.2005 - 06.2008",
    "kw": "162",
    "hp": "220",
    "cc": "1984",
    "engineCodes": "BUL",
    "KBA_Numbers": "7967323  7967AAG  0588AFE"
  },
  {
    "brand": "AUDI",
    "model": "A4 B7 (8EC) | A4 / S4",
    "engineType": "2.5 TDI",
    "madeYear": "11.2004 - 05.2006",
    "kw": "120",
    "hp": "163",
    "cc": "2496",
    "engineCodes": "BDG",
    "KBA_Numbers": "0588ADE  0588804"
  },
  {
    "brand": "AUDI",
    "model": "A4 B7 (8EC) | A4 / S4",
    "engineType": "2.7 TDI",
    "madeYear": "11.2005 - 06.2008",
    "kw": "120",
    "hp": "163",
    "cc": "2698",
    "engineCodes": "BSG",
    "KBA_Numbers": "0588AAH"
  },
  {
    "brand": "AUDI",
    "model": "A4 B7 (8EC) | A4 / S4",
    "engineType": "2.7 TDI",
    "madeYear": "01.2006 - 06.2008",
    "kw": "132",
    "hp": "180",
    "cc": "2698",
    "engineCodes": "BPP",
    "KBA_Numbers": "0588AAG"
  },
  {
    "brand": "AUDI",
    "model": "A4 B7 (8EC) | A4 / S4",
    "engineType": "3.0",
    "madeYear": "11.2004 - 05.2006",
    "kw": "160",
    "hp": "218",
    "cc": "2976",
    "engineCodes": "BBJ",
    "KBA_Numbers": ""
  },
  {
    "brand": "AUDI",
    "model": "A4 B7 (8EC) | A4 / S4",
    "engineType": "3.0 quattro",
    "madeYear": "11.2004 - 07.2006",
    "kw": "160",
    "hp": "218",
    "cc": "2976",
    "engineCodes": "BBJ",
    "KBA_Numbers": ""
  },
  {
    "brand": "AUDI",
    "model": "A4 B7 (8EC) | A4 / S4",
    "engineType": "3.0 TDI quattro",
    "madeYear": "11.2004 - 06.2008",
    "kw": "150",
    "hp": "204",
    "cc": "2967",
    "engineCodes": "BKN",
    "KBA_Numbers": "0588867  0588ADK"
  },
  {
    "brand": "AUDI",
    "model": "A4 B7 (8EC) | A4 / S4",
    "engineType": "3.0 TDI quattro",
    "madeYear": "01.2006 - 06.2008",
    "kw": "171",
    "hp": "233",
    "cc": "2967",
    "engineCodes": "ASB",
    "KBA_Numbers": "0588ADA  0588878"
  },
  {
    "brand": "AUDI",
    "model": "A4 B7 (8EC) | A4 / S4",
    "engineType": "3.2 FSI",
    "madeYear": "01.2005 - 06.2008",
    "kw": "188",
    "hp": "255",
    "cc": "3123",
    "engineCodes": "AUK",
    "KBA_Numbers": "0588ADB  0588869"
  },
  {
    "brand": "AUDI",
    "model": "A4 B7 (8EC) | A4 / S4",
    "engineType": "3.2 FSI quattro",
    "madeYear": "01.2005 - 06.2008",
    "kw": "188",
    "hp": "255",
    "cc": "3123",
    "engineCodes": "AUK",
    "KBA_Numbers": "0588ADC  0588870"
  },
  {
    "brand": "AUDI",
    "model": "A4 B7 (8EC) | A4 / S4",
    "engineType": "S4 quattro",
    "madeYear": "11.2004 - 06.2008",
    "kw": "253",
    "hp": "344",
    "cc": "4163",
    "engineCodes": "BBK",
    "KBA_Numbers": "0588ADD"
  },
  {
    "brand": "AUDI",
    "model": "A4 B7 Avant (8ED) | A4 / S4",
    "engineType": "2.0 TDI",
    "madeYear": "06.2006 - 06.2008",
    "kw": "120",
    "hp": "163",
    "cc": "1968",
    "engineCodes": "BVA",
    "KBA_Numbers": "0588AFO"
  },
  {
    "brand": "AUDI",
    "model": "A4 B7 Avant (8ED) | A4 / S4",
    "engineType": "2.0 TDI",
    "madeYear": "06.2006 - 06.2008",
    "kw": "125",
    "hp": "170",
    "cc": "1968",
    "engineCodes": "BRD",
    "KBA_Numbers": "0588AFJ"
  },
  {
    "brand": "AUDI",
    "model": "A4 B7 Avant (8ED) | A4 / S4",
    "engineType": "2.0 TDI quattro",
    "madeYear": "06.2006 - 06.2008",
    "kw": "120",
    "hp": "163",
    "cc": "1968",
    "engineCodes": "BVA",
    "KBA_Numbers": "0588AFP"
  },
  {
    "brand": "AUDI",
    "model": "A4 B7 Avant (8ED) | A4 / S4",
    "engineType": "2.0 TDI quattro",
    "madeYear": "06.2006 - 06.2008",
    "kw": "125",
    "hp": "170",
    "cc": "1968",
    "engineCodes": "BRD",
    "KBA_Numbers": "0588AFL"
  },
  {
    "brand": "AUDI",
    "model": "A4 B7 Avant (8ED) | A4 / S4",
    "engineType": "2.0 TFSI",
    "madeYear": "11.2004 - 06.2008",
    "kw": "147",
    "hp": "200",
    "cc": "1984",
    "engineCodes": "BWE  BGB  BPG",
    "KBA_Numbers": "0588ACR  0588865"
  },
  {
    "brand": "AUDI",
    "model": "A4 B7 Avant (8ED) | A4 / S4",
    "engineType": "2.0 TFSI",
    "madeYear": "06.2005 - 06.2008",
    "kw": "162",
    "hp": "220",
    "cc": "1984",
    "engineCodes": "BUL",
    "KBA_Numbers": "7967AAB  0588AEZ"
  },
  {
    "brand": "AUDI",
    "model": "A4 B7 Avant (8ED) | A4 / S4",
    "engineType": "2.0 TFSI",
    "madeYear": "10.2006 - 06.2008",
    "kw": "125",
    "hp": "170",
    "cc": "1984",
    "engineCodes": "BPJ  BYK",
    "KBA_Numbers": "0588AFW"
  },
  {
    "brand": "AUDI",
    "model": "A4 B7 Avant (8ED) | A4 / S4",
    "engineType": "2.0 TFSI quattro",
    "madeYear": "11.2004 - 06.2008",
    "kw": "147",
    "hp": "200",
    "cc": "1984",
    "engineCodes": "BWE  BGB  BWT",
    "KBA_Numbers": "0588ACS  0588866"
  },
  {
    "brand": "AUDI",
    "model": "A4 B7 Avant (8ED) | A4 / S4",
    "engineType": "2.0 TFSI quattro",
    "madeYear": "06.2005 - 06.2008",
    "kw": "162",
    "hp": "220",
    "cc": "1984",
    "engineCodes": "BUL",
    "KBA_Numbers": "7967AAC  0588AFA"
  },
  {
    "brand": "AUDI",
    "model": "A4 B7 Avant (8ED) | A4 / S4",
    "engineType": "2.5 TDI",
    "madeYear": "11.2004 - 05.2006",
    "kw": "120",
    "hp": "163",
    "cc": "2496",
    "engineCodes": "BDG",
    "KBA_Numbers": "0588ACO  0588805"
  },
  {
    "brand": "AUDI",
    "model": "A4 B7 Avant (8ED) | A4 / S4",
    "engineType": "2.7 TDi",
    "madeYear": "11.2005 - 03.2008",
    "kw": "120",
    "hp": "163",
    "cc": "2698",
    "engineCodes": "BSG",
    "KBA_Numbers": "0588AAE"
  },
  {
    "brand": "AUDI",
    "model": "A4 B7 Avant (8ED) | A4 / S4",
    "engineType": "2.7 TDI",
    "madeYear": "01.2006 - 06.2008",
    "kw": "132",
    "hp": "180",
    "cc": "2698",
    "engineCodes": "BPP",
    "KBA_Numbers": "0588AAD"
  },
  {
    "brand": "AUDI",
    "model": "A4 B7 Avant (8ED) | A4 / S4",
    "engineType": "3.0",
    "madeYear": "11.2004 - 05.2006",
    "kw": "160",
    "hp": "218",
    "cc": "2976",
    "engineCodes": "BBJ",
    "KBA_Numbers": ""
  },
  {
    "brand": "AUDI",
    "model": "A4 B7 Avant (8ED) | A4 / S4",
    "engineType": "3.0 quattro",
    "madeYear": "11.2004 - 07.2006",
    "kw": "160",
    "hp": "218",
    "cc": "2976",
    "engineCodes": "BBJ",
    "KBA_Numbers": ""
  },
  {
    "brand": "AUDI",
    "model": "A4 B7 Avant (8ED) | A4 / S4",
    "engineType": "3.0 TDI quattro",
    "madeYear": "11.2004 - 06.2008",
    "kw": "150",
    "hp": "204",
    "cc": "2967",
    "engineCodes": "BKN",
    "KBA_Numbers": "0588ACU  0588868"
  },
  {
    "brand": "AUDI",
    "model": "A4 B7 Avant (8ED) | A4 / S4",
    "engineType": "3.0 TDI quattro",
    "madeYear": "01.2006 - 06.2008",
    "kw": "171",
    "hp": "233",
    "cc": "2967",
    "engineCodes": "ASB",
    "KBA_Numbers": "0588ACK  0588877"
  },
  {
    "brand": "AUDI",
    "model": "A4 B7 Avant (8ED) | A4 / S4",
    "engineType": "3.2 FSI",
    "madeYear": "01.2005 - 06.2008",
    "kw": "188",
    "hp": "255",
    "cc": "3123",
    "engineCodes": "AUK",
    "KBA_Numbers": "0588ACL  0588871"
  },
  {
    "brand": "AUDI",
    "model": "A4 B7 Avant (8ED) | A4 / S4",
    "engineType": "3.2 FSI quattro",
    "madeYear": "01.2005 - 06.2008",
    "kw": "188",
    "hp": "255",
    "cc": "3123",
    "engineCodes": "AUK  BKH",
    "KBA_Numbers": "0588ACM  0588872"
  },
  {
    "brand": "AUDI",
    "model": "A4 B7 Avant (8ED) | A4 / S4",
    "engineType": "S4 quattro",
    "madeYear": "11.2004 - 06.2008",
    "kw": "253",
    "hp": "344",
    "cc": "4163",
    "engineCodes": "BBK",
    "KBA_Numbers": "0588ACN  0588824"
  },
  {
    "brand": "AUDI",
    "model": "A4 B7 Convertible (8HE) | A4 / S4",
    "engineType": "2.0 TFSI 16V",
    "madeYear": "01.2006 - 03.2009",
    "kw": "147",
    "hp": "200",
    "cc": "1984",
    "engineCodes": "BWE",
    "KBA_Numbers": "0588AAP"
  },
  {
    "brand": "AUDI",
    "model": "A4 B7 Convertible (8HE) | A4 / S4",
    "engineType": "2.7 TDI",
    "madeYear": "06.2006 - 03.2009",
    "kw": "132",
    "hp": "180",
    "cc": "2698",
    "engineCodes": "BPP",
    "KBA_Numbers": "0588AFG"
  },
  {
    "brand": "AUDI",
    "model": "A4 B7 Convertible (8HE) | A4 / S4",
    "engineType": "3.0 TDI quattro",
    "madeYear": "01.2006 - 03.2009",
    "kw": "150",
    "hp": "204",
    "cc": "2967",
    "engineCodes": "BKN",
    "KBA_Numbers": "0588AAM"
  },
  {
    "brand": "AUDI",
    "model": "A4 B7 Convertible (8HE) | A4 / S4",
    "engineType": "3.0 TDI quattro",
    "madeYear": "01.2006 - 03.2009",
    "kw": "171",
    "hp": "233",
    "cc": "2967",
    "engineCodes": "ASB",
    "KBA_Numbers": "0588AAJ"
  },
  {
    "brand": "AUDI",
    "model": "A4 B7 Convertible (8HE) | A4 / S4",
    "engineType": "3.2 FSI",
    "madeYear": "01.2006 - 03.2009",
    "kw": "188",
    "hp": "255",
    "cc": "3123",
    "engineCodes": "AUK",
    "KBA_Numbers": "0588AAK"
  },
  {
    "brand": "AUDI",
    "model": "A4 B7 Convertible (8HE) | A4 / S4",
    "engineType": "3.2 FSI quattro",
    "madeYear": "01.2006 - 03.2009",
    "kw": "188",
    "hp": "255",
    "cc": "3123",
    "engineCodes": "AUK  BKH",
    "KBA_Numbers": "0588AAL"
  },
  {
    "brand": "AUDI",
    "model": "A4 B7 Convertible (8HE) | A4 / S4",
    "engineType": "S4 quattro",
    "madeYear": "11.2005 - 03.2009",
    "kw": "253",
    "hp": "344",
    "cc": "4163",
    "engineCodes": "BBK  BHF",
    "KBA_Numbers": "0588859"
  },
  {
    "brand": "AUDI",
    "model": "A6 Allroad C6 (4FH)",
    "engineType": "2.7 TDI quattro",
    "madeYear": "03.2006 - 10.2008",
    "kw": "132",
    "hp": "180",
    "cc": "2698",
    "engineCodes": "BPP",
    "KBA_Numbers": "0588ABO"
  },
  {
    "brand": "AUDI",
    "model": "A6 Allroad C6 (4FH)",
    "engineType": "2.7 TDI quattro",
    "madeYear": "05.2006 - 08.2011",
    "kw": "120",
    "hp": "163",
    "cc": "2698",
    "engineCodes": "CAND  BSG",
    "KBA_Numbers": "0588AOY  0588ABQ"
  },
  {
    "brand": "AUDI",
    "model": "A6 Allroad C6 (4FH)",
    "engineType": "2.7 TDI quattro",
    "madeYear": "10.2008 - 08.2011",
    "kw": "140",
    "hp": "190",
    "cc": "2698",
    "engineCodes": "CANC",
    "KBA_Numbers": "0588AOX  0588AJN"
  },
  {
    "brand": "AUDI",
    "model": "A6 Allroad C6 (4FH)",
    "engineType": "3.0 TDI quattro",
    "madeYear": "05.2006 - 08.2011",
    "kw": "155",
    "hp": "211",
    "cc": "2967",
    "engineCodes": "CDYB  BNG",
    "KBA_Numbers": "0588APE  0588ABL"
  },
  {
    "brand": "AUDI",
    "model": "A6 Allroad C6 (4FH)",
    "engineType": "3.0 TDI quattro",
    "madeYear": "05.2006 - 10.2008",
    "kw": "171",
    "hp": "233",
    "cc": "2967",
    "engineCodes": "ASB",
    "KBA_Numbers": "0588ABA"
  },
  {
    "brand": "AUDI",
    "model": "A6 Allroad C6 (4FH)",
    "engineType": "3.0 TDI quattro",
    "madeYear": "10.2008 - 08.2011",
    "kw": "176",
    "hp": "240",
    "cc": "2967",
    "engineCodes": "CDYC  CDYA",
    "KBA_Numbers": "0588APD  0588AJJ"
  },
  {
    "brand": "AUDI",
    "model": "A6 Allroad C6 (4FH)",
    "engineType": "3.0 TFSI quattro",
    "madeYear": "10.2008 - 08.2011",
    "kw": "213",
    "hp": "290",
    "cc": "2995",
    "engineCodes": "CAJA",
    "KBA_Numbers": "0588AOU  0588AJR"
  },
  {
    "brand": "AUDI",
    "model": "A6 Allroad C6 (4FH)",
    "engineType": "3.2 FSI quattro",
    "madeYear": "05.2006 - 10.2008",
    "kw": "188",
    "hp": "255",
    "cc": "3123",
    "engineCodes": "AUK",
    "KBA_Numbers": "0588ABC"
  },
  {
    "brand": "AUDI",
    "model": "A6 Allroad C6 (4FH)",
    "engineType": "4.2 FSI quattro",
    "madeYear": "05.2006 - 12.2010",
    "kw": "257",
    "hp": "350",
    "cc": "4163",
    "engineCodes": "BVJ",
    "KBA_Numbers": "0588AOP  0588AAZ"
  },
  {
    "brand": "AUDI",
    "model": "A6 C6 (4F2) | A6 / S6",
    "engineType": "2.0 TDI",
    "madeYear": "07.2004 - 03.2011",
    "kw": "100",
    "hp": "136",
    "cc": "1968",
    "engineCodes": "BRF  BNA  CAGB",
    "KBA_Numbers": "0588874  0588894  0588ACB"
  },
  {
    "brand": "AUDI",
    "model": "A6 C6 (4F2) | A6 / S6",
    "engineType": "2.0 TDI",
    "madeYear": "07.2004 - 10.2008",
    "kw": "103",
    "hp": "140",
    "cc": "1968",
    "engineCodes": "BRE  BLB",
    "KBA_Numbers": "0588856  0588ABZ"
  },
  {
    "brand": "AUDI",
    "model": "A6 C6 (4F2) | A6 / S6",
    "engineType": "2.0 TDI",
    "madeYear": "09.2005 - 06.2006",
    "kw": "89",
    "hp": "121",
    "cc": "1968",
    "engineCodes": "BVG",
    "KBA_Numbers": "0588905  0588AAC"
  },
  {
    "brand": "AUDI",
    "model": "A6 C6 (4F2) | A6 / S6",
    "engineType": "2.0 TDI",
    "madeYear": "11.2008 - 03.2011",
    "kw": "125",
    "hp": "170",
    "cc": "1968",
    "engineCodes": "CAHA",
    "KBA_Numbers": "0588AJO"
  },
  {
    "brand": "AUDI",
    "model": "A6 C6 (4F2) | A6 / S6",
    "engineType": "2.0 TFSI",
    "madeYear": "06.2005 - 03.2011",
    "kw": "125",
    "hp": "170",
    "cc": "1984",
    "engineCodes": "BPJ",
    "KBA_Numbers": "0588901  0588ACD"
  },
  {
    "brand": "AUDI",
    "model": "A6 C6 (4F2) | A6 / S6",
    "engineType": "2.4",
    "madeYear": "05.2004 - 10.2008",
    "kw": "130",
    "hp": "177",
    "cc": "2393",
    "engineCodes": "BDW",
    "KBA_Numbers": "0588851  0588ABX"
  },
  {
    "brand": "AUDI",
    "model": "A6 C6 (4F2) | A6 / S6",
    "engineType": "2.4 quattro",
    "madeYear": "01.2005 - 10.2008",
    "kw": "130",
    "hp": "177",
    "cc": "2393",
    "engineCodes": "BDW",
    "KBA_Numbers": "0588875  0588ABY"
  },
  {
    "brand": "AUDI",
    "model": "A6 C6 (4F2) | A6 / S6",
    "engineType": "2.7 TDI",
    "madeYear": "11.2004 - 03.2011",
    "kw": "120",
    "hp": "163",
    "cc": "2698",
    "engineCodes": "CANB  BSG",
    "KBA_Numbers": "0588ACG  0588881  0588893"
  },
  {
    "brand": "AUDI",
    "model": "A6 C6 (4F2) | A6 / S6",
    "engineType": "2.7 TDI",
    "madeYear": "11.2004 - 10.2008",
    "kw": "132",
    "hp": "180",
    "cc": "2698",
    "engineCodes": "BPP",
    "KBA_Numbers": "0588ACE  0588876"
  },
  {
    "brand": "AUDI",
    "model": "A6 C6 (4F2) | A6 / S6",
    "engineType": "2.7 TDI",
    "madeYear": "10.2008 - 03.2011",
    "kw": "140",
    "hp": "190",
    "cc": "2698",
    "engineCodes": "CANA",
    "KBA_Numbers": "0588AJK"
  },
  {
    "brand": "AUDI",
    "model": "A6 C6 (4F2) | A6 / S6",
    "engineType": "2.7 TDI quattro",
    "madeYear": "11.2004 - 10.2008",
    "kw": "132",
    "hp": "180",
    "cc": "2698",
    "engineCodes": "BPP",
    "KBA_Numbers": "0588ACF  0588903"
  },
  {
    "brand": "AUDI",
    "model": "A6 C6 (4F2) | A6 / S6",
    "engineType": "2.7 TDI quattro",
    "madeYear": "06.2005 - 03.2011",
    "kw": "120",
    "hp": "163",
    "cc": "2698",
    "engineCodes": "CAND  BSG",
    "KBA_Numbers": "0588ACH  0588899"
  },
  {
    "brand": "AUDI",
    "model": "A6 C6 (4F2) | A6 / S6",
    "engineType": "2.7 TDI quattro",
    "madeYear": "10.2008 - 03.2011",
    "kw": "140",
    "hp": "190",
    "cc": "2698",
    "engineCodes": "CANC",
    "KBA_Numbers": "0588AJL"
  },
  {
    "brand": "AUDI",
    "model": "A6 C6 (4F2) | A6 / S6",
    "engineType": "2.8 FSI",
    "madeYear": "11.2006 - 10.2008",
    "kw": "154",
    "hp": "210",
    "cc": "2773",
    "engineCodes": "BDX",
    "KBA_Numbers": "0588AFX"
  },
  {
    "brand": "AUDI",
    "model": "A6 C6 (4F2) | A6 / S6",
    "engineType": "2.8 FSI",
    "madeYear": "10.2008 - 03.2011",
    "kw": "140",
    "hp": "190",
    "cc": "2773",
    "engineCodes": "CCDA",
    "KBA_Numbers": "0588AJE"
  },
  {
    "brand": "AUDI",
    "model": "A6 C6 (4F2) | A6 / S6",
    "engineType": "2.8 FSI",
    "madeYear": "10.2008 - 03.2011",
    "kw": "162",
    "hp": "220",
    "cc": "2773",
    "engineCodes": "CCEA",
    "KBA_Numbers": "0588AJA"
  },
  {
    "brand": "AUDI",
    "model": "A6 C6 (4F2) | A6 / S6",
    "engineType": "2.8 FSI quattro",
    "madeYear": "06.2007 - 10.2008",
    "kw": "154",
    "hp": "210",
    "cc": "2773",
    "engineCodes": "BDX",
    "KBA_Numbers": "0588AGJ"
  },
  {
    "brand": "AUDI",
    "model": "A6 C6 (4F2) | A6 / S6",
    "engineType": "2.8 FSI quattro",
    "madeYear": "10.2008 - 03.2011",
    "kw": "140",
    "hp": "190",
    "cc": "2773",
    "engineCodes": "CCDA",
    "KBA_Numbers": "0588AJF"
  },
  {
    "brand": "AUDI",
    "model": "A6 C6 (4F2) | A6 / S6",
    "engineType": "2.8 FSI quattro",
    "madeYear": "10.2008 - 03.2011",
    "kw": "162",
    "hp": "220",
    "cc": "2773",
    "engineCodes": "CCEA",
    "KBA_Numbers": "0588AJB"
  },
  {
    "brand": "AUDI",
    "model": "A6 C6 (4F2) | A6 / S6",
    "engineType": "3.0",
    "madeYear": "08.2004 - 05.2006",
    "kw": "160",
    "hp": "218",
    "cc": "2976",
    "engineCodes": "BBJ",
    "KBA_Numbers": "0588855  0588ABV"
  },
  {
    "brand": "AUDI",
    "model": "A6 C6 (4F2) | A6 / S6",
    "engineType": "3.0 quattro",
    "madeYear": "05.2004 - 05.2006",
    "kw": "160",
    "hp": "218",
    "cc": "2976",
    "engineCodes": "BBJ",
    "KBA_Numbers": "0588ABW"
  },
  {
    "brand": "AUDI",
    "model": "A6 C6 (4F2) | A6 / S6",
    "engineType": "3.0 TDI quattro",
    "madeYear": "05.2004 - 03.2011",
    "kw": "155",
    "hp": "211",
    "cc": "2967",
    "engineCodes": "CDYB  BNG",
    "KBA_Numbers": "0588854  0588ACC"
  },
  {
    "brand": "AUDI",
    "model": "A6 C6 (4F2) | A6 / S6",
    "engineType": "3.0 TDI quattro",
    "madeYear": "05.2004 - 05.2006",
    "kw": "165",
    "hp": "225",
    "cc": "2967",
    "engineCodes": "BMK",
    "KBA_Numbers": "0588852  0588ACA"
  },
  {
    "brand": "AUDI",
    "model": "A6 C6 (4F2) | A6 / S6",
    "engineType": "3.0 TDI quattro",
    "madeYear": "06.2006 - 10.2008",
    "kw": "171",
    "hp": "233",
    "cc": "2967",
    "engineCodes": "ASB",
    "KBA_Numbers": "0588AAS"
  },
  {
    "brand": "AUDI",
    "model": "A6 C6 (4F2) | A6 / S6",
    "engineType": "3.0 TDI quattro",
    "madeYear": "10.2008 - 03.2011",
    "kw": "176",
    "hp": "240",
    "cc": "2967",
    "engineCodes": "CDYC  CDYA",
    "KBA_Numbers": "0588AJI"
  },
  {
    "brand": "AUDI",
    "model": "A6 C6 (4F2) | A6 / S6",
    "engineType": "3.0 TFSI quattro",
    "madeYear": "10.2008 - 03.2011",
    "kw": "213",
    "hp": "290",
    "cc": "2995",
    "engineCodes": "CAJA",
    "KBA_Numbers": "0588AJQ"
  },
  {
    "brand": "AUDI",
    "model": "A6 C6 (4F2) | A6 / S6",
    "engineType": "3.0 TFSI quattro",
    "madeYear": "10.2008 - 03.2011",
    "kw": "220",
    "hp": "299",
    "cc": "2995",
    "engineCodes": "CCAA",
    "KBA_Numbers": ""
  },
  {
    "brand": "AUDI",
    "model": "A6 C6 (4F2) | A6 / S6",
    "engineType": "3.2 FSI",
    "madeYear": "05.2004 - 05.2009",
    "kw": "188",
    "hp": "255",
    "cc": "3123",
    "engineCodes": "AUK  BKH",
    "KBA_Numbers": "0588848  0588ABS"
  },
  {
    "brand": "AUDI",
    "model": "A6 C6 (4F2) | A6 / S6",
    "engineType": "3.2 FSI",
    "madeYear": "05.2009 - 03.2011",
    "kw": "195",
    "hp": "265",
    "cc": "3197",
    "engineCodes": "CALA",
    "KBA_Numbers": ""
  },
  {
    "brand": "AUDI",
    "model": "A6 C6 (4F2) | A6 / S6",
    "engineType": "3.2 FSI quattro",
    "madeYear": "05.2004 - 10.2008",
    "kw": "188",
    "hp": "255",
    "cc": "3123",
    "engineCodes": "AUK  BKH",
    "KBA_Numbers": "0588849  0588ABT"
  },
  {
    "brand": "AUDI",
    "model": "A6 C6 (4F2) | A6 / S6",
    "engineType": "4.2 FSI quattro",
    "madeYear": "06.2006 - 03.2011",
    "kw": "257",
    "hp": "350",
    "cc": "4163",
    "engineCodes": "BVJ",
    "KBA_Numbers": "0588AFS  0588AAQ"
  },
  {
    "brand": "AUDI",
    "model": "A6 C6 (4F2) | A6 / S6",
    "engineType": "4.2 quattro",
    "madeYear": "to 03.2011",
    "kw": "246",
    "hp": "335",
    "cc": "4163",
    "engineCodes": "BAT  BNK",
    "KBA_Numbers": "0588850  0588ABR  0588ABU"
  },
  {
    "brand": "AUDI",
    "model": "A6 C6 Avant (4F5)",
    "engineType": "2.0 TDI",
    "madeYear": "06.2005 - 08.2011",
    "kw": "100",
    "hp": "136",
    "cc": "1968",
    "engineCodes": "BRF  BNA  CAGB",
    "KBA_Numbers": "0588AOR  0588ABK"
  },
  {
    "brand": "AUDI",
    "model": "A6 C6 Avant (4F5)",
    "engineType": "2.0 TDI",
    "madeYear": "06.2005 - 10.2008",
    "kw": "103",
    "hp": "140",
    "cc": "1968",
    "engineCodes": "BRE  BLB",
    "KBA_Numbers": "0588887  0588ABI"
  },
  {
    "brand": "AUDI",
    "model": "A6 C6 Avant (4F5)",
    "engineType": "2.0 TDI",
    "madeYear": "09.2005 - 06.2006",
    "kw": "89",
    "hp": "121",
    "cc": "1968",
    "engineCodes": "BVG",
    "KBA_Numbers": "0588906  0588AAB"
  },
  {
    "brand": "AUDI",
    "model": "A6 C6 Avant (4F5)",
    "engineType": "2.0 TDI",
    "madeYear": "10.2008 - 08.2011",
    "kw": "125",
    "hp": "170",
    "cc": "1968",
    "engineCodes": "CAHA",
    "KBA_Numbers": "0588AOS  0588AJP"
  },
  {
    "brand": "AUDI",
    "model": "A6 C6 Avant (4F5)",
    "engineType": "2.0 TDI",
    "madeYear": "04.2009 - 08.2011",
    "kw": "120",
    "hp": "163",
    "cc": "1968",
    "engineCodes": "CAHB",
    "KBA_Numbers": "0588AOT  0588AKJ"
  },
  {
    "brand": "AUDI",
    "model": "A6 C6 Avant (4F5)",
    "engineType": "2.0 TFSI",
    "madeYear": "06.2005 - 08.2011",
    "kw": "125",
    "hp": "170",
    "cc": "1984",
    "engineCodes": "BPJ",
    "KBA_Numbers": "0588AOO  0588902  0588ABM"
  },
  {
    "brand": "AUDI",
    "model": "A6 C6 Avant (4F5)",
    "engineType": "2.4",
    "madeYear": "03.2005 - 10.2008",
    "kw": "130",
    "hp": "177",
    "cc": "2393",
    "engineCodes": "BDW",
    "KBA_Numbers": "0588885  0588ABG"
  },
  {
    "brand": "AUDI",
    "model": "A6 C6 Avant (4F5)",
    "engineType": "2.4 quattro",
    "madeYear": "03.2005 - 10.2008",
    "kw": "130",
    "hp": "177",
    "cc": "2393",
    "engineCodes": "BDW",
    "KBA_Numbers": "0588886  0588ABH"
  },
  {
    "brand": "AUDI",
    "model": "A6 C6 Avant (4F5)",
    "engineType": "2.7 TDI",
    "madeYear": "03.2005 - 08.2011",
    "kw": "120",
    "hp": "163",
    "cc": "2698",
    "engineCodes": "CANB  BSG",
    "KBA_Numbers": "0588AOW  0588ABP"
  },
  {
    "brand": "AUDI",
    "model": "A6 C6 Avant (4F5)",
    "engineType": "2.7 TDI",
    "madeYear": "03.2005 - 10.2008",
    "kw": "132",
    "hp": "180",
    "cc": "2698",
    "engineCodes": "BPP",
    "KBA_Numbers": "0588889  0588ABN"
  },
  {
    "brand": "AUDI",
    "model": "A6 C6 Avant (4F5)",
    "engineType": "2.7 TDI",
    "madeYear": "10.2008 - 08.2011",
    "kw": "140",
    "hp": "190",
    "cc": "2698",
    "engineCodes": "CANA",
    "KBA_Numbers": "0588AOV  0588AJM"
  },
  {
    "brand": "AUDI",
    "model": "A6 C6 Avant (4F5)",
    "engineType": "2.7 TDI quattro",
    "madeYear": "11.2004 - 10.2008",
    "kw": "132",
    "hp": "180",
    "cc": "2698",
    "engineCodes": "BPP",
    "KBA_Numbers": "0588904  0588ABO"
  },
  {
    "brand": "AUDI",
    "model": "A6 C6 Avant (4F5)",
    "engineType": "2.7 TDI quattro",
    "madeYear": "06.2005 - 08.2011",
    "kw": "120",
    "hp": "163",
    "cc": "2698",
    "engineCodes": "CAND  BSG",
    "KBA_Numbers": "0588900  0588ABQ"
  },
  {
    "brand": "AUDI",
    "model": "A6 C6 Avant (4F5)",
    "engineType": "2.7 TDI quattro",
    "madeYear": "10.2008 - 08.2011",
    "kw": "140",
    "hp": "190",
    "cc": "2698",
    "engineCodes": "CANC",
    "KBA_Numbers": "0588AJN"
  },
  {
    "brand": "AUDI",
    "model": "A6 C6 Avant (4F5)",
    "engineType": "2.8 FSI",
    "madeYear": "11.2006 - 10.2008",
    "kw": "154",
    "hp": "210",
    "cc": "2773",
    "engineCodes": "BDX",
    "KBA_Numbers": "0588AFY"
  },
  {
    "brand": "AUDI",
    "model": "A6 C6 Avant (4F5)",
    "engineType": "2.8 FSI",
    "madeYear": "10.2008 - 08.2011",
    "kw": "140",
    "hp": "190",
    "cc": "2773",
    "engineCodes": "CCDA",
    "KBA_Numbers": "0588AOZ  0588AJG"
  },
  {
    "brand": "AUDI",
    "model": "A6 C6 Avant (4F5)",
    "engineType": "2.8 FSI",
    "madeYear": "10.2008 - 08.2011",
    "kw": "162",
    "hp": "220",
    "cc": "2773",
    "engineCodes": "CCEA",
    "KBA_Numbers": "0588APB  0588ANS  0588AJC"
  },
  {
    "brand": "AUDI",
    "model": "A6 C6 Avant (4F5)",
    "engineType": "2.8 FSI quattro",
    "madeYear": "06.2007 - 10.2008",
    "kw": "154",
    "hp": "210",
    "cc": "2773",
    "engineCodes": "BDX",
    "KBA_Numbers": "0588AGI"
  },
  {
    "brand": "AUDI",
    "model": "A6 C6 Avant (4F5)",
    "engineType": "2.8 FSI quattro",
    "madeYear": "10.2008 - 08.2011",
    "kw": "140",
    "hp": "190",
    "cc": "2773",
    "engineCodes": "CCDA",
    "KBA_Numbers": "0588APA  0588AJH"
  },
  {
    "brand": "AUDI",
    "model": "A6 C6 Avant (4F5)",
    "engineType": "2.8 FSI quattro",
    "madeYear": "10.2008 - 08.2011",
    "kw": "162",
    "hp": "220",
    "cc": "2773",
    "engineCodes": "CCEA",
    "KBA_Numbers": "0588APC  0588AJD"
  },
  {
    "brand": "AUDI",
    "model": "A6 C6 Avant (4F5)",
    "engineType": "3.0",
    "madeYear": "03.2005 - 05.2006",
    "kw": "160",
    "hp": "218",
    "cc": "2976",
    "engineCodes": "BBJ",
    "KBA_Numbers": "0588890  0588ABE"
  },
  {
    "brand": "AUDI",
    "model": "A6 C6 Avant (4F5)",
    "engineType": "3.0 quattro",
    "madeYear": "03.2005 - 05.2006",
    "kw": "160",
    "hp": "218",
    "cc": "2976",
    "engineCodes": "BBJ",
    "KBA_Numbers": "0588891  0588ABF"
  },
  {
    "brand": "AUDI",
    "model": "A6 C6 Avant (4F5)",
    "engineType": "3.0 TDI quattro",
    "madeYear": "03.2005 - 08.2011",
    "kw": "155",
    "hp": "211",
    "cc": "2967",
    "engineCodes": "CDYB  BNG",
    "KBA_Numbers": "0588892  0588ABL"
  },
  {
    "brand": "AUDI",
    "model": "A6 C6 Avant (4F5)",
    "engineType": "3.0 TDI quattro",
    "madeYear": "03.2005 - 05.2006",
    "kw": "165",
    "hp": "225",
    "cc": "2967",
    "engineCodes": "BMK",
    "KBA_Numbers": "0588888  0588ABJ"
  },
  {
    "brand": "AUDI",
    "model": "A6 C6 Avant (4F5)",
    "engineType": "3.0 TDI quattro",
    "madeYear": "06.2006 - 10.2008",
    "kw": "171",
    "hp": "233",
    "cc": "2967",
    "engineCodes": "ASB",
    "KBA_Numbers": "0588ABA"
  },
  {
    "brand": "AUDI",
    "model": "A6 C6 Avant (4F5)",
    "engineType": "3.0 TDI quattro",
    "madeYear": "10.2008 - 08.2011",
    "kw": "176",
    "hp": "240",
    "cc": "2967",
    "engineCodes": "CDYC  CDYA",
    "KBA_Numbers": "0588AJJ"
  },
  {
    "brand": "AUDI",
    "model": "A6 C6 Avant (4F5)",
    "engineType": "3.0 TFSI quattro",
    "madeYear": "10.2008 - 08.2011",
    "kw": "213",
    "hp": "290",
    "cc": "2995",
    "engineCodes": "CAJA",
    "KBA_Numbers": "0588AJR"
  },
  {
    "brand": "AUDI",
    "model": "A6 C6 Avant (4F5)",
    "engineType": "3.0 TFSI quattro",
    "madeYear": "10.2008 - 08.2011",
    "kw": "220",
    "hp": "299",
    "cc": "2995",
    "engineCodes": "CCAA",
    "KBA_Numbers": ""
  },
  {
    "brand": "AUDI",
    "model": "A6 C6 Avant (4F5)",
    "engineType": "3.2 FSI",
    "madeYear": "03.2005 - 10.2008",
    "kw": "188",
    "hp": "255",
    "cc": "3123",
    "engineCodes": "AUK",
    "KBA_Numbers": "0588ABB  0588882"
  },
  {
    "brand": "AUDI",
    "model": "A6 C6 Avant (4F5)",
    "engineType": "3.2 FSI quattro",
    "madeYear": "03.2005 - 10.2008",
    "kw": "188",
    "hp": "255",
    "cc": "3123",
    "engineCodes": "AUK  BKH",
    "KBA_Numbers": "0588883"
  },
  {
    "brand": "AUDI",
    "model": "A6 C6 Avant (4F5)",
    "engineType": "4.2 FSI quattro",
    "madeYear": "06.2006 - 08.2011",
    "kw": "257",
    "hp": "350",
    "cc": "4163",
    "engineCodes": "BVJ",
    "KBA_Numbers": "0588AAZ"
  },
  {
    "brand": "AUDI",
    "model": "A6 C6 Avant (4F5)",
    "engineType": "4.2 quattro",
    "madeYear": "03.2005 - 05.2006",
    "kw": "246",
    "hp": "335",
    "cc": "4163",
    "engineCodes": "BAT",
    "KBA_Numbers": "0588884  0588ABD"
  },
  {
    "brand": "AUDI",
    "model": "A8 D3 (4E2, 4E8) | A8 / S8 | A8L",
    "engineType": "2.8 FSI",
    "madeYear": "08.2007 - 07.2010",
    "kw": "154",
    "hp": "210",
    "cc": "2773",
    "engineCodes": "BDX",
    "KBA_Numbers": "0588AGM"
  },
  {
    "brand": "AUDI",
    "model": "A8 D3 (4E2, 4E8) | A8 / S8 | A8L",
    "engineType": "3.0",
    "madeYear": "07.2003 - 05.2006",
    "kw": "160",
    "hp": "218",
    "cc": "2976",
    "engineCodes": "BBJ",
    "KBA_Numbers": ""
  },
  {
    "brand": "AUDI",
    "model": "A8 D3 (4E2, 4E8) | A8 / S8 | A8L",
    "engineType": "3.0",
    "madeYear": "07.2003 - 05.2005",
    "kw": "162",
    "hp": "220",
    "cc": "2976",
    "engineCodes": "ASN",
    "KBA_Numbers": "0588816  0588AEB"
  },
  {
    "brand": "AUDI",
    "model": "A8 D3 (4E2, 4E8) | A8 / S8 | A8L",
    "engineType": "3.0 quattro",
    "madeYear": "07.2003 - 05.2005",
    "kw": "162",
    "hp": "220",
    "cc": "2976",
    "engineCodes": "ASN",
    "KBA_Numbers": "0588AEI  0588817"
  },
  {
    "brand": "AUDI",
    "model": "A8 D3 (4E2, 4E8) | A8 / S8 | A8L",
    "engineType": "3.0 TDI quattro",
    "madeYear": "08.2003 - 07.2010",
    "kw": "171",
    "hp": "233",
    "cc": "2967",
    "engineCodes": "ASB",
    "KBA_Numbers": "0588843  0588ADZ"
  },
  {
    "brand": "AUDI",
    "model": "A8 D3 (4E2, 4E8) | A8 / S8 | A8L",
    "engineType": "3.0 TDI quattro",
    "madeYear": "11.2003 - 07.2010",
    "kw": "155",
    "hp": "211",
    "cc": "2967",
    "engineCodes": "BNG",
    "KBA_Numbers": "0588847  0588AEE"
  },
  {
    "brand": "AUDI",
    "model": "A8 D3 (4E2, 4E8) | A8 / S8 | A8L",
    "engineType": "3.2 FSI",
    "madeYear": "06.2005 - 07.2010",
    "kw": "191",
    "hp": "260",
    "cc": "3123",
    "engineCodes": "BPK",
    "KBA_Numbers": "0588AEF  0588896"
  },
  {
    "brand": "AUDI",
    "model": "A8 D3 (4E2, 4E8) | A8 / S8 | A8L",
    "engineType": "3.2 FSI quattro",
    "madeYear": "06.2005 - 07.2010",
    "kw": "191",
    "hp": "260",
    "cc": "3123",
    "engineCodes": "BPK",
    "KBA_Numbers": "0588AEG  0588897"
  },
  {
    "brand": "AUDI",
    "model": "A8 D3 (4E2, 4E8) | A8 / S8 | A8L",
    "engineType": "3.7 quattro",
    "madeYear": "10.2002 - 05.2006",
    "kw": "206",
    "hp": "280",
    "cc": "3697",
    "engineCodes": "BFL",
    "KBA_Numbers": "0588819  0588AEJ"
  },
  {
    "brand": "AUDI",
    "model": "A8 D3 (4E2, 4E8) | A8 / S8 | A8L",
    "engineType": "4.0 TDI quattro",
    "madeYear": "05.2003 - 07.2005",
    "kw": "202",
    "hp": "275",
    "cc": "3936",
    "engineCodes": "ASE",
    "KBA_Numbers": "0588832  0588AEA"
  },
  {
    "brand": "AUDI",
    "model": "A8 D3 (4E2, 4E8) | A8 / S8 | A8L",
    "engineType": "4.2 FSI quattro",
    "madeYear": "06.2006 - 07.2010",
    "kw": "257",
    "hp": "350",
    "cc": "4163",
    "engineCodes": "BVJ",
    "KBA_Numbers": "0588AAR"
  },
  {
    "brand": "AUDI",
    "model": "A8 D3 (4E2, 4E8) | A8 / S8 | A8L",
    "engineType": "4.2 quattro",
    "madeYear": "10.2002 - 07.2010",
    "kw": "246",
    "hp": "335",
    "cc": "4172",
    "engineCodes": "BFM",
    "KBA_Numbers": "0588818  0588AEC"
  },
  {
    "brand": "AUDI",
    "model": "A8 D3 (4E2, 4E8) | A8 / S8 | A8L",
    "engineType": "4.2 TDI quattro",
    "madeYear": "01.2005 - 06.2005",
    "kw": "235",
    "hp": "320",
    "cc": "4134",
    "engineCodes": "BMC",
    "KBA_Numbers": ""
  },
  {
    "brand": "AUDI",
    "model": "A8 D3 (4E2, 4E8) | A8 / S8 | A8L",
    "engineType": "4.2 TDI quattro",
    "madeYear": "07.2005 - 07.2010",
    "kw": "240",
    "hp": "326",
    "cc": "4134",
    "engineCodes": "BVN",
    "KBA_Numbers": "0588AEH  0588898"
  },
  {
    "brand": "AUDI",
    "model": "A8 D3 (4E2, 4E8) | A8 / S8 | A8L",
    "engineType": "6.0 W12 quattro",
    "madeYear": "12.2003 - 07.2010",
    "kw": "331",
    "hp": "450",
    "cc": "5998",
    "engineCodes": "BHT",
    "KBA_Numbers": "0588844  0588AED  0588AEK"
  },
  {
    "brand": "SEAT",
    "model": "EXEO (3R2)",
    "engineType": "1.8 T",
    "madeYear": "12.2008 - 05.2010",
    "kw": "110",
    "hp": "150",
    "cc": "1781",
    "engineCodes": "CFMA",
    "KBA_Numbers": "7593ADU"
  },
  {
    "brand": "SEAT",
    "model": "EXEO (3R2)",
    "engineType": "2.0 TDI",
    "madeYear": "12.2008 - 05.2013",
    "kw": "88",
    "hp": "120",
    "cc": "1968",
    "engineCodes": "CAGC  CJCC",
    "KBA_Numbers": "7593AED"
  },
  {
    "brand": "SEAT",
    "model": "EXEO (3R2)",
    "engineType": "2.0 TDI",
    "madeYear": "12.2008 - 05.2013",
    "kw": "105",
    "hp": "143",
    "cc": "1968",
    "engineCodes": "CAGA  CJCA",
    "KBA_Numbers": "7593ADR"
  },
  {
    "brand": "SEAT",
    "model": "EXEO (3R2)",
    "engineType": "2.0 TDI",
    "madeYear": "02.2009 - 05.2013",
    "kw": "125",
    "hp": "170",
    "cc": "1968",
    "engineCodes": "CAHA  CGLB",
    "KBA_Numbers": "7593ADS"
  },
  {
    "brand": "SEAT",
    "model": "EXEO (3R2)",
    "engineType": "2.0 TFSI",
    "madeYear": "03.2009 - 05.2013",
    "kw": "147",
    "hp": "200",
    "cc": "1984",
    "engineCodes": "BWE",
    "KBA_Numbers": "7593ADV"
  },
  {
    "brand": "SEAT",
    "model": "EXEO (3R2)",
    "engineType": "2.0 TFSI",
    "madeYear": "05.2010 - 05.2013",
    "kw": "155",
    "hp": "211",
    "cc": "1984",
    "engineCodes": "CDND",
    "KBA_Numbers": "7593AFD"
  },
  {
    "brand": "SEAT",
    "model": "EXEO ST (3R5)",
    "engineType": "2.0 TFSI",
    "madeYear": "06.2009 - 05.2013",
    "kw": "147",
    "hp": "200",
    "cc": "1984",
    "engineCodes": "BWE",
    "KBA_Numbers": "7593ADY"
  },
  {
    "brand": "SEAT",
    "model": "EXEO ST (3R5)",
    "engineType": "2.0 TFSI",
    "madeYear": "05.2010 - 05.2013",
    "kw": "155",
    "hp": "211",
    "cc": "1984",
    "engineCodes": "CDND",
    "KBA_Numbers": "7593AFF"
  }
]