{
  "reference": "180068",
  "id": "180068",
  "name": "Fren balata seti, diskli fren",
  "brand": "ICER",
  "wvaNumbers": [
    "20073",
    "D54-798"
  ],
  "brand_oe_map": {
    "AUTOBIANCHI": [
      "7 906 05",
      "9 993 935 3"
    ],
    "FIAT": [
      "4 174 992",
      "4 204 050",
      "4 218 573",
      "4 236 412",
      "4 255 797",
      "4 309 780",
      "4 341 532",
      "4 370 874",
      "4 386 012",
      "4 434 816",
      "4 434 897",
      "5 888 149",
      "5 888 154",
      "5 888 573",
      "5 888 574",
      "5 951 897"
    ],
    "FSO": [
      "030 633",
      "039 532",
      "039 533",
      "059 957",
      "655 792 725"
    ],
    "INNOCENTI": [
      "9 993 935 3"
    ],
    "LANCIA": [
      "4 434 816",
      "5 888 149",
      "5 888 154",
      "9 993 935 3"
    ],
    "SEAT": [
      "3 915 580",
      "3 980 604",
      "4 341 534",
      "4 434 816",
      "SE1 271 650 05 A"
    ],
    "ZASTAVA": [
      "4 218 573",
      "4 423 980",
      "4 660 454"
    ]
  },
  "eanNumber": "8424073006561",
  "dimensions": {
    "width1": "108,9",
    "width2": null,
    "height1": "39,1",
    "height2": null,
    "thickness1": "17,3",
    "thickness2": null,
    "manufacturerRestriction": "",
    "checkmark": "KBA 60714",
    "SVHC": ""
  }
}