{
  "reference": "08.4750.44",
  "id": "08.4750.44",
  "name": "Fren diski PRIME LINE",
  "brand": "BREMBO",
  "brand_oe_map": {
    "MERCEDES-BENZ": [
      "2024210212",
      "A2024210212"
    ]
  },
  "eanNumber": "8020584013182",
  "disc": {
    "Type": [
      "dolu"
    ],
    "ThicknessValues": [
      "12"
    ],
    "MinimumThicknessValues": [
      "10"
    ],
    "Surface": [],
    "HeightValues": [
      "44"
    ],
    "InnerDiameter": [],
    "OuterDiameter": [
      "284"
    ],
    "BoltHoleCircle": [],
    "NumberOfHoles": [
      "5"
    ],
    "AxleVersion": [],
    "TechnicalInformationNumber": [],
    "TestMark": [],
    "Diameter": [],
    "Thickness": [],
    "SupplementaryInfo": [
      "Cıvatalar ile"
    ],
    "CenteringDiameter": [
      "67"
    ],
    "HoleArrangement_HoleNumber": [],
    "WheelBoltBoreDiameter": [],
    "Machining": [],
    "TighteningTorque": [
      "110"
    ],
    "Weight": [],
    "Color": [],
    "ThreadSize": []
  }
}